{
  "1697178177119": "[Rank of All Defensive Skills]",
  "1697250557581": "[Armor X% Shadow Resistance]",
  "1697630133094": "[Rank of Decrepify]",
  "1697667138610": "[Rank of Iron Maiden][Rank of Decrepify]",
  "1697680049012": "[Maximum Evade Charges]",
  "1697689469194": "[Rank of Blight][Rank of Blood Lance]",
  "1697693383200": "[Maximum Evade Charge]",
  "1697693437174": "[Maximum Evade Charge]",
  "1697696669866": "[Block Chance]",
  "1697700170533": "[Maximum Evade Charges]",
  "1697702908405": "[Rank of Iron Maiden]",
  "1697703645090": "[Rank of All Macabre Skills][Rank of All Curse Skills]",
  "1697706145652": "[Damage to Shadow Damage Over Time-Affected Enemies]",
  "1697713838297": "[Rank of Ice Blades]",
  "1697714742665": "[Maximum Evade Charges]",
  "1697717556427": "[Rank of the Brute Force Passive]",
  "1697719134148": "[Damage to Crowdntrolled Enemies]",
  "1697722815647": "[Rank of Chain Lightning][Rank of Charged Bolts]",
  "1697726660561": "[Ranks of All Agility Skills][Ranks of All Imbuement Skills]",
  "1697729088763": "[Rank of All Macabre Skills][Rank of All Curse Skills]",
  "1697729761098": "[Rank of the Natural Disaster Passive]",
  "1697733890300": "[Maximum Evade Charges]",
  "1697734545023": "[Damage Reduction from Shadow Damage Over Time-Affected Enemies][Rank of All Macabre Skills]",
  "1697744516176": "[Rank of Earthen Bulwark]",
  "1697760464426": "[Block Chance]",
  "1697766232330": "[Rank of Firewall][Rank of Ball Lightning]",
  "1697776716424": "[Damage while in Human Form]",
  "1697779055225": "[Maximum Evade Charges]",
  "1697795677757": "[Rank of Shadow Imbuement]",
  "1697795718479": "[Rank of Flurry][Rank of Twisting Blades]",
  "1697798527399": "[Maximum Evade Charge]",
  "1697808322352": "[Damage Reduction from Burning Enemies]",
  "1697809452010": "[Maximum Evade Charge][Rank of Frost Nova]",
  "1697814953215": "[Damage to Shadow Damage Over Time-Affected Enemies]",
  "1697833439652": "[Rank of the Exploit Passive]",
  "1697838726398": "[Maximum Evade Charges]",
  "1697869818170": "[Damage to Shadow Damage Over Time-Affected Enemies]",
  "1697872545029": "[Resource]",
  "1697877050027": "[Damage to Shadow Damage Over Time-Affected Enemies]",
  "1697883091180": "[Damage to Shadow Damage Over Time-Affected Enemies]",
  "1697899031180": "[Marks of Teleport]",
  "1697904880066": "[Maximum Evade Charges]",
  "1697907010916": "[Damage Reduction from Shadow Damage Over Time-Affected Enemies]",
  "1697907858423": "[Damage to Shadow Damage Over Time-Affected Enemies]",
  "1697908356712": "[Core Skill Damage Socket]",
  "1697909780289": "[Maximum Evade Charges]",
  "1697910149040": "[Rank of the Quickshift Passive]",
  "1697910187948": "[Rank of the Envenom Passive]",
  "1697910220860": "[Damage Reduction from Poisoned Enemies]",
  "1697910257071": "[Rank of the Crushing Earth Passive]",
  "1697911068682": "[Care Skill Damage]",
  "1697912169222": "[Damage Reduction from Shadow Damage Over Time-Affected Enemies]",
  "1697912282163": "[Damage to Shadow Damage Over Time-Affected Enemies]",
  "1697914415471": "[Minions Inherit X% of Your Thorns]",
  "1697936691232": "[Damage Reduction from Poisoned Enemies]",
  "1697936974803": "[Damage Reduction from Poisoned Enemies]",
  "1697947385866": "[Rank of the Impetus Passive]",
  "1697948390783": "[Damage Reduction from Shadow Damage Over Time-Affected Enemies]",
  "1697948871324": "[Damage Reduction from Poisoned Enemies]",
  "1697950095402": "[Rank of the Impetus Passive]",
  "1697950555210": "[Damage Reduction from Poisoned Enemies]",
  "1697956699183": "[Maximum Evade Charges]",
  "1697969487608": "[Rank of Rend]",
  "1697969526894": "[Rank of Charge][Rank of Leap]",
  "1697971088577": "[Damage to Shadow Damage Over Time-Affected Enemies]",
  "1697974433432": "[Critical Strike Chance X% Resource Generation Socket]",
  "1697974988004": "[Damage to Shadow Damage Over Time-Affected Enemies]",
  "1697980131863": "[Armor]",
  "1697980213730": "[Rank of Caltrops]",
  "1697981874292": "[Damage Reduction from Poisoned Enemies]",
  "1698022904250": "[Damage Reduction from Shadow Damage Over Time-Affected Enemies]",
  "1698026198915": "[Rank of All Defensive Skills][Rank of All Companion Skills]",
  "1698035403500": "[Rank of Blizzard]",
  "1698044098967": "[Maximum Evade Charges]",
  "1698047056619": "[Enemies]",
  "1698052274714": "[Damage Reduction from Bleeding Enemies]",
  "1698052596572": "[Maximum Evade Charges]",
  "1698053213561": "[Damage Reduction from Shadow Damage Over Time-Affected Enemies]",
  "1698076517877": "[Maximum Evade Charge]",
  "1698076570942": "[Maximum Evade Charge]",
  "1698076582731": "[Rank of All Brawling Skills]",
  "1698076637723": "[Rank of All Weapon Mastery Skills]",
  "1698079904325": "[Seconds]",
  "1698088901481": "[Rank of Kick]",
  "1698090138970": "[Rank of Leap]",
  "1698090284474": "[Rank of All Weapon Mastery Skills]",
  "1698108970084": "[Rank of Iron Maiden]",
  "1698115613648": "[Damage Reduction from Shadow Damage Over Time-Affected Enemies]",
  "1698115655839": "[Damage Reduction from Shadow Damage Over Time-Affected Enemies]",
  "1698115905574": "[Rank of Smoke Grenade]",
  "1698116352348": "[Damage Reduction from Shadow Damage Over Time-Affected Enemies]",
  "1698117000889": "[Damage Reduction from Shadow Damage Over Time-Affected Enemies]",
  "1698117106943": "[Rank of All Weapon Mastery Skills]",
  "1698124720737": "[Block Chance]",
  "1698133946510": "[Rank of All Subterfuge Skills]",
  "1698137088747": "[Rank of Barrage][Rank of Penetrating Shot]",
  "1698140714866": "[Damage to Shadow Damage Over Time-Affected Enemies]",
  "1698140927555": "[Damage to Shadow Damage Over Time-Affected Enemies]",
  "1698142394148": "[Damage to Close Enemies X Intelligence Socket]",
  "1698142729106": "[Lucky Hit Chance Socket]",
  "1698142769859": "[Damage to Shadow Damage Over Time-Affected Enemies]",
  "1698150448637": "[Overpower Damage with Two- Handed Bludgeoning Weapons]",
  "1698159998468": "[Rank of Trample]",
  "1698162220395": "[Rank of Ice Blades]",
  "1698164459208": "[Rank of All Mastery Skills]",
  "1698164537272": "[Damage Reduction from Burning Enemies]",
  "1698165298022": "[Maximum Evade Charges]",
  "1698169952968": "[Maximum Evade Charges]",
  "1698170169865": "[Maximum Evade Charges]",
  "1698171129148": "[Overpower Damage Socket]",
  "1698214124045": "[Block Chance]",
  "1698217080328": "[Rank of All Defensive Skills]",
  "1698217570020": "[Damage Reduction from Poisoned Enemies]",
  "1698219736958": "[Damage to Shadow Damage Over Time-Affected Enemies]",
  "1698233127037": "[Rank of Bone Spear]",
  "1698240613053": "[Overpower Damage with Two- Handed Bludgeoning Weapons]",
  "1698250421175": "[Damage to Shadow Damage Over Time-Affected Enemies]",
  "1698250636778": "[Damage to Shadow Damage Over Time-Affected Enemies]",
  "1698250884442": "[Damage Reduction from Bleeding Enemies]",
  "1698251208319": "[Rank of All Corpse Skills][Rank of the Tides of Blood Passive]",
  "1698252144554": "[Damage to Shadow Damage Over Time-Affected Enemies]",
  "1698289513514": "[Rank of the Amplify Damage Passive]",
  "1698291391492": "[Damage Reduction from Poisoned Enemies]",
  "1698302561172": "[Damage while in Human Form]",
  "1698302639405": "[Rank of Death Blow]",
  "1698302887512": "[Damage Reduction from Bleeding Enemies]",
  "1698302987247": "[Rank of Death Blow]",
  "1698303216522": "[Rank of Whirlwind]",
  "1698304421199": "[Damage Reduction from Shadow Damage Over Time- Affected Enemies]",
  "1698382368827": "[Maximum Evade Charges]",
  "1698383645407": "[Damage Reduction from Burning Enemies]",
  "1698388599372": "[Damage to Shadow Damage Over Time-Affected Enemies]",
  "1698388676274": "[Damage to Shadow Damage Over Time-Affected Enemies]",
  "1698401951971": "[Maximum Evade Charges]",
  "1698414701074": "[Damage Reduction from Burning Enemies][Rank of All Mastery Skills]",
  "1698461043020": "[Damage Reduction from Poisoned Enemies]",
  "1698477635610": "[Maximum Evade Charges]",
  "1698485514181": "[Rank of All Curse Skills]",
  "1698485919410": "[Damage to Shadow Damage Over Time-Affected Enemies]",
  "1698486015876": "[Damage to Shadow Damage Over Time-Affected Enemies]",
  "1698487286872": "[Damage to Shadow Damage Over Time-Affected Enemies]",
  "1698496219185": "[Damage to Clase Enemies]",
  "1698499431971": "[Rank of All Weapon Mastery Skills]",
  "1698501679477": "[Minions Inherit X% of Your Thorns]",
  "1698510793346": "[Basic Skill Attack Speed Socket]",
  "1698511316114": "[Rank of Blight]",
  "1698512001368": "[Basic Skill Attack Speed Socket]",
  "1698515503780": "[Rank of All Companion Skills]",
  "1698515515352": "[Rank of All Defensive Skills]",
  "1698520306125": "[Rank of the Defiance Passive]",
  "1698520306553": "[Rank of the Nature's Reach Passive]",
  "1698546734054": "[Damage Reduction from Burning Enemies]",
  "1698553864371": "[Damage to Shadow Damage Over Time-Affected Enemies]",
  "1698561106030": "[Damage to Shadow Damage Over Time-Affected Enemies]",
  "1698561841029": "[Damage Reduction from Shadow Damage Over Time-Affected Enemies]",
  "1698562269902": "[Damage to Shadow Damage Over Time-Affected Enemies]",
  "1698562615183": "[Maximum Evade Charges]",
  "1698563163700": "[Damage to Shadow Damage Over Time-Affected Enemies]",
  "1698563369754": "[Damage to Shadow Damage Over Time-Affected Enemies]",
  "1698569804524": "[Ranks of All Imbuement Skills]",
  "1698569805747": "[Ranks of All Imbuement Skills][Rank of the Exploit Passive]",
  "1698569807268": "[Ranks of All Imbuement Skills]",
  "1698569845086": "[Damage Reduction from Bleeding Enemies]",
  "1698570212383": "[Damage to Shadow Damage Over Time-Affected Enemies]",
  "1698570949834": "[Damage to Shadow Damage Over Time-Affected Enemies]",
  "1698571241739": "[Damage to Shadow Damage Over Time-Affected Enemies]",
  "1698573839706": "[Rank of Landslide]",
  "1698573978079": "[Damage Reduction from Burning Enemies]",
  "1698581068974": "[Damage Reduction from Poisoned Enemies]",
  "1698582506974": "[Rank of the Elemental Dominance Passive]",
  "1698582531336": "[Rank of the Conjuration Mastery Passive][Resistance to][Rank of the Elemen Passive]",
  "1698589656646": "[Damage Reduction from Bleeding Enemies][Rank of All Defensive Skills]",
  "1698590199443": "[Ranks of All Agility Skills]",
  "1698590233213": "[Damage Reduction from Poisoned Enemies]",
  "1698594001689": "[Damage while in Human Form]",
  "1698595291385": "[Rank of Double Swing]",
  "1698604894242": "[Damage Reduction from Burning Enemies]",
  "1698627383661": "[Damage Reduction from Poisoned Enemies]",
  "1698628978147": "[Damage Reduction from Poisoned Enemies]",
  "1698628982987": "[Damage Reduction from Poisoned Enemies]",
  "1698628984699": "[Damage Reduction from Poisoned Enemies]",
  "1698628985667": "[Damage Reduction from Poisoned Enemies]",
  "1698628996115": "[Damage Reduction from Poisoned Enemies]",
  "1698629005669": "[Damage Reduction from Poisoned Enemies]",
  "1698674546377": "[Damage Reduction from Poisoned Enemies]",
  "1698711833259": "[Damage Reduction from Poisoned Enemies]",
  "1698711980987": "[Damage Reduction from Poisoned Enemies]",
  "1698747795313": "[Damage Reduction from Burning Enemies]",
  "1698750498899": "[Damage Reduction from Poisoned Enemies]",
  "1698750788384": "[Damage Reduction from Poisoned Enemies]",
  "1698750939244": "[Damage Reduction from Poisoned Enemies]"
}