[
 {
  "name": "B",
  "builds": [
   {
    "name": "Ball Lightning Sorcerer Endgame Guide",
    "slots": [
     {
      "slotName": "Wand",
      "itemPower": 820,
      "stats": [
       {
        "name": "Lucky Hit Chance",
        "isPercent": true,
        "min": 15,
        "max": 15,
        "value": 15
       },
       {
        "name": "Vulnerable Damage",
        "isPercent": true,
        "min": 10.5,
        "max": 21,
        "value": 21
       },
       {
        "name": "Critical Strike Damage",
        "isPercent": true,
        "min": 15.8,
        "max": 26.2,
        "value": 26.2
       },
       {
        "name": "Lightning Critical Strike Damage",
        "isPercent": true,
        "min": 15.8,
        "max": 26.2,
        "value": 26.2
       },
       {
        "name": "Intelligence",
        "isPercent": false,
        "min": 57,
        "max": 78,
        "value": 78
       }
      ]
     },
     {
      "slotName": "Amulet",
      "itemPower": 820,
      "stats": [
       {
        "name": "Resistance to All Elements",
        "isPercent": true,
        "min": 26.5,
        "max": 26.5,
        "value": 26.5
       },
       {
        "name": "Ranks of All Defensive Skills",
        "isPercent": false,
        "min": 1,
        "max": 3,
        "value": 3
       },
       {
        "name": "Mana Cost Reduction",
        "isPercent": true,
        "min": 13.9,
        "max": 23.7,
        "value": 23.7
       },
       {
        "name": "Cooldown Reduction",
        "isPercent": true,
        "min": 6.2,
        "max": 10.3,
        "value": 10.3
       },
       {
        "name": "Ranks of All Mastery Skills",
        "isPercent": false,
        "min": 1,
        "max": 3,
        "value": 3
       }
      ]
     },
     {
      "slotName": "Chest Armor",
      "itemPower": 820,
      "stats": [
       {
        "name": "Intelligence",
        "isPercent": false,
        "min": 42,
        "max": 63,
        "value": 63
       },
       {
        "name": "Damage to Close Enemies",
        "isPercent": true,
        "min": 24.8,
        "max": 35.3,
        "value": 35.3
       },
       {
        "name": "Damage to Stunned Enemies",
        "isPercent": true,
        "min": 24.8,
        "max": 35.3,
        "value": 35.3
       },
       {
        "name": "Rank of the Glass Cannon Passive",
        "isPercent": false,
        "min": 1,
        "max": 1,
        "value": 1
       }
      ]
     },
     {
      "slotName": "Boots",
      "itemPower": 820,
      "stats": [
       {
        "name": "Max Evade Charges",
        "isPercent": false,
        "min": 3,
        "max": 3,
        "value": 3
       },
       {
        "name": "Mana Cost Reduction",
        "isPercent": true,
        "min": 6.2,
        "max": 10.3,
        "value": 10.3
       },
       {
        "name": "Ranks of Frost Nova",
        "isPercent": false,
        "min": 3,
        "max": 4,
        "value": 4
       },
       {
        "name": "Ranks of Teleport",
        "isPercent": false,
        "min": 3,
        "max": 4,
        "value": 4
       },
       {
        "name": "Movement Speed",
        "isPercent": true,
        "min": 15.8,
        "max": 26.2,
        "value": 26.2
       }
      ]
     },
     {
      "slotName": "Gloves",
      "itemPower": 820,
      "stats": [
       {
        "name": "Critical Strike Chance",
        "isPercent": true,
        "min": 4.5,
        "max": 12,
        "value": 12
       },
       {
        "name": "Attack Speed",
        "isPercent": true,
        "min": 6.6,
        "max": 15,
        "value": 15
       },
       {
        "name": "Lightning Critical Strike Damage",
        "isPercent": true,
        "min": 15.8,
        "max": 26.2,
        "value": 26.2
       }
      ]
     },
     {
      "slotName": "Helm",
      "itemPower": 820,
      "stats": [
       {
        "name": "Cooldown Reduction",
        "isPercent": true,
        "min": 6.2,
        "max": 10.3,
        "value": 10.3
       },
       {
        "name": "Maximum Mana",
        "isPercent": false,
        "min": 8,
        "max": 20,
        "value": 20
       },
       {
        "name": "Maximum Life",
        "isPercent": false,
        "min": 605,
        "max": 1310,
        "value": 1310
       },
       {
        "name": "Lucky Hit Chance while You Have a Barrier",
        "isPercent": true,
        "min": 6.6,
        "max": 15,
        "value": 15
       }
      ]
     },
     {
      "slotName": "Focus",
      "itemPower": 820,
      "stats": [
       {
        "name": "Cooldown Reduction",
        "isPercent": true,
        "min": 10.3,
        "max": 10.3,
        "value": 10.3
       },
       {
        "name": "Cooldown Reduction",
        "isPercent": true,
        "min": 6.2,
        "max": 10.3,
        "value": 10.3
       },
       {
        "name": "Resource Generation",
        "isPercent": true,
        "min": 7.6,
        "max": 18.5,
        "value": 18.5
       },
       {
        "name": "Mana Cost Reduction",
        "isPercent": true,
        "min": 6.2,
        "max": 10.3,
        "value": 10.3
       }
      ]
     },
     {
      "slotName": "Pants",
      "itemPower": 820,
      "stats": [
       {
        "name": "Damage Reduction",
        "isPercent": true,
        "min": 4.6,
        "max": 10.7,
        "value": 10.7
       },
       {
        "name": "Damage Reduction from Close Enemies",
        "isPercent": true,
        "min": 10.3,
        "max": 20.2,
        "value": 20.2
       },
       {
        "name": "Damage Reduction from Distant Enemies",
        "isPercent": true,
        "min": 13.9,
        "max": 23.7,
        "value": 23.7
       },
       {
        "name": "Ranks of Ball Lightning",
        "isPercent": false,
        "min": 3,
        "max": 4,
        "value": 4
       }
      ]
     },
     {
      "slotName": "Ring",
      "itemPower": 820,
      "stats": [
       {
        "name": "Fire Resistance",
        "isPercent": true,
        "min": 35,
        "max": 35,
        "value": 35
       },
       {
        "name": "Cold Resistance",
        "isPercent": true,
        "min": 35,
        "max": 35,
        "value": 35
       },
       {
        "name": "Resource Generation",
        "isPercent": true,
        "min": 7.6,
        "max": 18.5,
        "value": 18.5
       },
       {
        "name": "Critical Strike Damage",
        "isPercent": true,
        "min": 15.8,
        "max": 26.2,
        "value": 26.2
       },
       {
        "name": "Critical Strike Chance",
        "isPercent": true,
        "min": 2.7,
        "max": 7.5,
        "value": 7.5
       },
       {
        "name": "Vulnerable Damage",
        "isPercent": true,
        "min": 10.5,
        "max": 21,
        "value": 21
       }
      ]
     },
     {
      "slotName": "Ring",
      "itemPower": 820,
      "stats": [
       {
        "name": "Fire Resistance",
        "isPercent": true,
        "min": 35,
        "max": 35,
        "value": 35
       },
       {
        "name": "Cold Resistance",
        "isPercent": true,
        "min": 35,
        "max": 35,
        "value": 35
       },
       {
        "name": "Resource Generation",
        "isPercent": true,
        "min": 7.6,
        "max": 18.5,
        "value": 18.5
       },
       {
        "name": "Critical Strike Damage",
        "isPercent": true,
        "min": 15.8,
        "max": 26.2,
        "value": 26.2
       },
       {
        "name": "Lightning Critical Strike Damage",
        "isPercent": true,
        "min": 15.8,
        "max": 26.2,
        "value": 26.2
       },
       {
        "name": "Vulnerable Damage",
        "isPercent": true,
        "min": 10.5,
        "max": 21,
        "value": 21
       }
      ]
     }
    ]
   },
   {
    "name": "Blight Corpse Explosion Necromancer Endgame Guide",
    "slots": [
     {
      "slotName": "Sword",
      "itemPower": 800,
      "stats": [
       {
        "name": "Critical Strike Damage",
        "isPercent": true,
        "min": 21,
        "max": 21,
        "value": 52.5
       },
       {
        "name": "Critical Strike Damage",
        "isPercent": true,
        "min": 31.5,
        "max": 52.5,
        "value": 52.5
       },
       {
        "name": "All Stats",
        "isPercent": false,
        "min": 60,
        "max": 84,
        "value": 84
       },
       {
        "name": "Vulnerable Damage",
        "isPercent": true,
        "min": 21,
        "max": 42,
        "value": 42
       },
       {
        "name": "Damage to Affected By Shadow Damage Over Time Enemies",
        "isPercent": true,
        "min": 21,
        "max": 42,
        "value": 42
       }
      ]
     },
     {
      "slotName": "Amulet",
      "itemPower": 800,
      "stats": [
       {
        "name": "Resistance to All Elements",
        "isPercent": true,
        "min": 26.5,
        "max": 26.5,
        "value": 26.5
       },
       {
        "name": "Ranks of All Corpse Skills",
        "isPercent": false,
        "min": 1,
        "max": 3,
        "value": 3
       },
       {
        "name": "Movement Speed",
        "isPercent": true,
        "min": 15.8,
        "max": 26.2,
        "value": 26.2
       },
       {
        "name": "Cooldown Reduction",
        "isPercent": true,
        "min": 6.2,
        "max": 10.3,
        "value": 10.3
       },
       {
        "name": "Total Armor",
        "isPercent": true,
        "min": 3,
        "max": 7.2,
        "value": 7.2
       }
      ]
     },
     {
      "slotName": "Chest Armor",
      "itemPower": 800,
      "stats": [
       {
        "name": "Damage Reduction",
        "isPercent": true,
        "min": 4.6,
        "max": 10.7,
        "value": 10.7
       },
       {
        "name": "Maximum Life",
        "isPercent": false,
        "min": 559,
        "max": 1211,
        "value": 1211
       },
       {
        "name": "Total Armor",
        "isPercent": true,
        "min": 3,
        "max": 7.2,
        "value": 7.2
       },
       {
        "name": "Damage Reduction from Close Enemies",
        "isPercent": true,
        "min": 10.3,
        "max": 20.2,
        "value": 20.2
       }
      ]
     },
     {
      "slotName": "Boots",
      "itemPower": 800,
      "stats": [
       {
        "name": "Movement Speed",
        "isPercent": true,
        "min": 15.8,
        "max": 26.2,
        "value": 26.2
       },
       {
        "name": "Ranks of Corpse Tendrils",
        "isPercent": false,
        "min": 3,
        "max": 4,
        "value": 4
       },
       {
        "name": "Dodge Chance",
        "isPercent": true,
        "min": 4.5,
        "max": 8.6,
        "value": 8.6
       },
       {
        "name": "All Stats",
        "isPercent": false,
        "min": 15,
        "max": 27,
        "value": 27
       }
      ]
     },
     {
      "slotName": "Gloves",
      "itemPower": 800,
      "stats": [
       {
        "name": "Critical Strike Chance",
        "isPercent": true,
        "min": 4.5,
        "max": 12,
        "value": 12
       },
       {
        "name": "Attack Speed",
        "isPercent": true,
        "min": 6.6,
        "max": 15,
        "value": 15
       },
       {
        "name": "Ranks of Blight",
        "isPercent": false,
        "min": 3,
        "max": 4,
        "value": 4
       },
       {
        "name": "Lucky Hit Chance",
        "isPercent": true,
        "min": 8.1,
        "max": 16.5,
        "value": 16.5
       }
      ]
     },
     {
      "slotName": "Helm",
      "itemPower": 800,
      "stats": [
       {
        "name": "Maximum Life",
        "isPercent": false,
        "min": 559,
        "max": 1211,
        "value": 1211
       },
       {
        "name": "Total Armor",
        "isPercent": true,
        "min": 3,
        "max": 7.2,
        "value": 7.2
       },
       {
        "name": "Cooldown Reduction",
        "isPercent": true,
        "min": 6.2,
        "max": 10.3,
        "value": 10.3
       },
       {
        "name": "Lucky Hit Chance while You Have a Barrier",
        "isPercent": true,
        "min": 6.6,
        "max": 15,
        "value": 15
       }
      ]
     },
     {
      "slotName": "Pants",
      "itemPower": 800,
      "stats": [
       {
        "name": "Ranks of Corpse Explosion",
        "isPercent": false,
        "min": 3,
        "max": 4,
        "value": 4
       },
       {
        "name": "Damage Reduction from Close Enemies",
        "isPercent": true,
        "min": 10.3,
        "max": 20.2,
        "value": 20.2
       },
       {
        "name": "Damage Reduction from Enemies That Are Affected By Shadow Damage Over Time",
        "isPercent": true,
        "min": 7.4,
        "max": 17.4,
        "value": 17.4
       },
       {
        "name": "Total Armor",
        "isPercent": true,
        "min": 3,
        "max": 7.2,
        "value": 7.2
       }
      ]
     },
     {
      "slotName": "Ring",
      "itemPower": 800,
      "stats": [
       {
        "name": "Fire Resistance",
        "isPercent": true,
        "min": 35,
        "max": 35,
        "value": 35
       },
       {
        "name": "Cold Resistance",
        "isPercent": true,
        "min": 35,
        "max": 35,
        "value": 35
       },
       {
        "name": "Critical Strike Chance",
        "isPercent": true,
        "min": 2.7,
        "max": 7.5,
        "value": 7.5
       },
       {
        "name": "Critical Strike Damage",
        "isPercent": true,
        "min": 15.8,
        "max": 26.2,
        "value": 26.2
       },
       {
        "name": "Lucky Hit Chance",
        "isPercent": true,
        "min": 4.8,
        "max": 9,
        "value": 9
       },
       {
        "name": "Vulnerable Damage",
        "isPercent": true,
        "min": 10.5,
        "max": 21,
        "value": 21
       }
      ]
     },
     {
      "slotName": "Ring",
      "itemPower": 800,
      "stats": [
       {
        "name": "Lightning Resistance",
        "isPercent": true,
        "min": 35,
        "max": 35,
        "value": 35
       },
       {
        "name": "Poison Resistance",
        "isPercent": true,
        "min": 35,
        "max": 35,
        "value": 35
       },
       {
        "name": "Vulnerable Damage",
        "isPercent": true,
        "min": 10.5,
        "max": 21,
        "value": 21
       },
       {
        "name": "Maximum Life",
        "isPercent": false,
        "min": 559,
        "max": 1211,
        "value": 1211
       },
       {
        "name": "Critical Strike Chance",
        "isPercent": true,
        "min": 2.7,
        "max": 7.5,
        "value": 7.5
       },
       {
        "name": "Critical Strike Damage",
        "isPercent": true,
        "min": 15.8,
        "max": 26.2,
        "value": 26.2
       }
      ]
     }
    ]
   },
   {
    "name": "Blood Lance Necromancer Endgame Guide",
    "slots": [
     {
      "slotName": "Wand",
      "itemPower": 800,
      "stats": [
       {
        "name": "Lucky Hit Chance",
        "isPercent": true,
        "min": 15,
        "max": 15,
        "value": 15
       },
       {
        "name": "Overpower Damage",
        "isPercent": true,
        "min": 31.5,
        "max": 63,
        "value": 63
       },
       {
        "name": "All Stats",
        "isPercent": false,
        "min": 30,
        "max": 42,
        "value": 42
       },
       {
        "name": "Ultimate Skill Damage",
        "isPercent": true,
        "min": 21,
        "max": 31.5,
        "value": 31.5
       },
       {
        "name": "Intelligence",
        "isPercent": false,
        "min": 57,
        "max": 78,
        "value": 78
       }
      ]
     },
     {
      "slotName": "Amulet",
      "itemPower": 800,
      "stats": [
       {
        "name": "Resistance to All Elements",
        "isPercent": true,
        "min": 26.5,
        "max": 26.5,
        "value": 26.5
       },
       {
        "name": "Essence Cost Reduction",
        "isPercent": true,
        "min": 13.9,
        "max": 23.7,
        "value": 23.7
       },
       {
        "name": "Total Armor",
        "isPercent": true,
        "min": 3,
        "max": 7.2,
        "value": 7.2
       },
       {
        "name": "Ranks of the Tides of Blood Passive",
        "isPercent": false,
        "min": 1,
        "max": 3,
        "value": 3
       },
       {
        "name": "Movement Speed",
        "isPercent": true,
        "min": 15.8,
        "max": 26.2,
        "value": 26.2
       }
      ]
     },
     {
      "slotName": "Chest Armor",
      "itemPower": 800,
      "stats": [
       {
        "name": "Total Armor",
        "isPercent": true,
        "min": 3,
        "max": 7.2,
        "value": 7.2
       },
       {
        "name": "Maximum Life",
        "isPercent": false,
        "min": 559,
        "max": 1211,
        "value": 1211
       },
       {
        "name": "Damage Reduction while Fortified",
        "isPercent": true,
        "min": 7.3,
        "max": 15.3,
        "value": 15.3
       },
       {
        "name": "Damage Reduction",
        "isPercent": true,
        "min": 4.6,
        "max": 10.7,
        "value": 10.7
       }
      ]
     },
     {
      "slotName": "Boots",
      "itemPower": 800,
      "stats": [
       {
        "name": "Max Evade Charges",
        "isPercent": false,
        "min": 3,
        "max": 3,
        "value": 3
       },
       {
        "name": "Movement Speed",
        "isPercent": true,
        "min": 15.8,
        "max": 26.2,
        "value": 26.2
       },
       {
        "name": "Essence Cost Reduction",
        "isPercent": true,
        "min": 6.2,
        "max": 10.3,
        "value": 10.3
       },
       {
        "name": "Ranks of Corpse Tendrils",
        "isPercent": false,
        "min": 3,
        "max": 4,
        "value": 4
       },
       {
        "name": "Fortify Generation",
        "isPercent": true,
        "min": 22.5,
        "max": 33,
        "value": 33
       }
      ]
     },
     {
      "slotName": "Gloves",
      "itemPower": 800,
      "stats": [
       {
        "name": "Overpower Damage",
        "isPercent": true,
        "min": 31.5,
        "max": 63,
        "value": 63
       },
       {
        "name": "Lucky Hit Chance",
        "isPercent": true,
        "min": 8.1,
        "max": 16.5,
        "value": 16.5
       },
       {
        "name": "Attack Speed",
        "isPercent": true,
        "min": 6.6,
        "max": 15,
        "value": 15
       }
      ]
     },
     {
      "slotName": "Helm",
      "itemPower": 800,
      "stats": [
       {
        "name": "Maximum Life",
        "isPercent": false,
        "min": 559,
        "max": 1211,
        "value": 1211
       },
       {
        "name": "Total Armor",
        "isPercent": true,
        "min": 3,
        "max": 7.2,
        "value": 7.2
       },
       {
        "name": "Cooldown Reduction",
        "isPercent": true,
        "min": 6.2,
        "max": 10.3,
        "value": 10.3
       },
       {
        "name": "Willpower",
        "isPercent": false,
        "min": 42,
        "max": 63,
        "value": 63
       }
      ]
     },
     {
      "slotName": "Shield",
      "itemPower": 800,
      "stats": [
       {
        "name": "Block Chance",
        "isPercent": true,
        "min": 30,
        "max": 30,
        "value": 30
       },
       {
        "name": "Blocked Damage Reduction",
        "isPercent": true,
        "min": 30,
        "max": 30,
        "value": 90
       },
       {
        "name": "Main Hand Weapon Damage",
        "isPercent": true,
        "min": 120,
        "max": 120,
        "value": 120
       },
       {
        "name": "Thorns",
        "isPercent": false,
        "min": 978,
        "max": 978,
        "value": 978
       },
       {
        "name": "Maximum Life",
        "isPercent": false,
        "min": 559,
        "max": 1211,
        "value": 1211
       },
       {
        "name": "Resource Generation",
        "isPercent": true,
        "min": 7.6,
        "max": 18.5,
        "value": 18.5
       },
       {
        "name": "Essence Cost Reduction",
        "isPercent": true,
        "min": 6.2,
        "max": 10.3,
        "value": 10.3
       }
      ]
     },
     {
      "slotName": "Pants",
      "itemPower": 800,
      "stats": [
       {
        "name": "Maximum Life",
        "isPercent": false,
        "min": 559,
        "max": 1211,
        "value": 1211
       },
       {
        "name": "Total Armor",
        "isPercent": true,
        "min": 3,
        "max": 7.2,
        "value": 7.2
       },
       {
        "name": "Damage Reduction while Fortified",
        "isPercent": true,
        "min": 7.3,
        "max": 15.3,
        "value": 15.3
       },
       {
        "name": "Ranks of Blood Mist",
        "isPercent": false,
        "min": 3,
        "max": 4,
        "value": 4
       }
      ]
     },
     {
      "slotName": "Ring",
      "itemPower": 800,
      "stats": [
       {
        "name": "Fire Resistance",
        "isPercent": true,
        "min": 35,
        "max": 35,
        "value": 35
       },
       {
        "name": "Cold Resistance",
        "isPercent": true,
        "min": 35,
        "max": 35,
        "value": 35
       },
       {
        "name": "Maximum Life",
        "isPercent": false,
        "min": 559,
        "max": 1211,
        "value": 1211
       },
       {
        "name": "Lucky Hit Chance",
        "isPercent": true,
        "min": 4.8,
        "max": 9,
        "value": 9
       },
       {
        "name": "Overpower Damage",
        "isPercent": true,
        "min": 21,
        "max": 42,
        "value": 42
       },
       {
        "name": "Resource Generation",
        "isPercent": true,
        "min": 7.6,
        "max": 18.5,
        "value": 18.5
       }
      ]
     },
     {
      "slotName": "Ring",
      "itemPower": 800,
      "stats": [
       {
        "name": "Lightning Resistance",
        "isPercent": true,
        "min": 35,
        "max": 35,
        "value": 35
       },
       {
        "name": "Poison Resistance",
        "isPercent": true,
        "min": 35,
        "max": 35,
        "value": 35
       },
       {
        "name": "Maximum Life",
        "isPercent": false,
        "min": 559,
        "max": 1211,
        "value": 1211
       },
       {
        "name": "Lucky Hit Chance",
        "isPercent": true,
        "min": 4.8,
        "max": 9,
        "value": 9
       },
       {
        "name": "Overpower Damage",
        "isPercent": true,
        "min": 21,
        "max": 42,
        "value": 42
       },
       {
        "name": "Resource Generation",
        "isPercent": true,
        "min": 7.6,
        "max": 18.5,
        "value": 18.5
       }
      ]
     }
    ]
   },
   {
    "name": "Chain Lightning Sorcerer Endgame Guide",
    "slots": [
     {
      "slotName": "Dagger",
      "itemPower": 800,
      "stats": [
       {
        "name": "Damage to Close Enemies",
        "isPercent": true,
        "min": 30,
        "max": 30,
        "value": 30
       },
       {
        "name": "Intelligence",
        "isPercent": false,
        "min": 57,
        "max": 78,
        "value": 78
       },
       {
        "name": "Critical Strike Damage",
        "isPercent": true,
        "min": 15.8,
        "max": 26.2,
        "value": 26.2
       },
       {
        "name": "Lightning Critical Strike Damage",
        "isPercent": true,
        "min": 15.8,
        "max": 26.2,
        "value": 26.2
       },
       {
        "name": "Vulnerable Damage",
        "isPercent": true,
        "min": 10.5,
        "max": 21,
        "value": 21
       }
      ]
     },
     {
      "slotName": "Amulet",
      "itemPower": 800,
      "stats": [
       {
        "name": "Resistance to All Elements",
        "isPercent": true,
        "min": 26.5,
        "max": 26.5,
        "value": 26.5
       },
       {
        "name": "Ranks of All Defensive Skills",
        "isPercent": false,
        "min": 1,
        "max": 3,
        "value": 3
       },
       {
        "name": "Cooldown Reduction",
        "isPercent": true,
        "min": 6.2,
        "max": 10.3,
        "value": 10.3
       },
       {
        "name": "Mana Cost Reduction",
        "isPercent": true,
        "min": 13.9,
        "max": 23.7,
        "value": 23.7
       },
       {
        "name": "Ranks of the Devouring Blaze Passive",
        "isPercent": false,
        "min": 1,
        "max": 3,
        "value": 3
       }
      ]
     },
     {
      "slotName": "Chest Armor",
      "itemPower": 800,
      "stats": [
       {
        "name": "Intelligence",
        "isPercent": false,
        "min": 42,
        "max": 63,
        "value": 63
       },
       {
        "name": "Damage to Close Enemies",
        "isPercent": true,
        "min": 24.8,
        "max": 35.3,
        "value": 35.3
       },
       {
        "name": "Damage to Stunned Enemies",
        "isPercent": true,
        "min": 24.8,
        "max": 35.3,
        "value": 35.3
       },
       {
        "name": "Rank of the Glass Cannon Passive",
        "isPercent": false,
        "min": 1,
        "max": 1,
        "value": 1
       }
      ]
     },
     {
      "slotName": "Boots",
      "itemPower": 800,
      "stats": [
       {
        "name": "Ranks of Frost Nova",
        "isPercent": false,
        "min": 3,
        "max": 4,
        "value": 4
       },
       {
        "name": "Ranks of Teleport",
        "isPercent": false,
        "min": 3,
        "max": 4,
        "value": 4
       },
       {
        "name": "Movement Speed",
        "isPercent": true,
        "min": 15.8,
        "max": 26.2,
        "value": 26.2
       },
       {
        "name": "Mana Cost Reduction",
        "isPercent": true,
        "min": 6.2,
        "max": 10.3,
        "value": 10.3
       }
      ]
     },
     {
      "slotName": "Gloves",
      "itemPower": 800,
      "stats": [
       {
        "name": "Critical Strike Chance",
        "isPercent": true,
        "min": 4.5,
        "max": 12,
        "value": 12
       },
       {
        "name": "Lightning Critical Strike Damage",
        "isPercent": true,
        "min": 15.8,
        "max": 26.2,
        "value": 26.2
       },
       {
        "name": "Attack Speed",
        "isPercent": true,
        "min": 6.6,
        "max": 15,
        "value": 15
       },
       {
        "name": "Ranks of Chain Lightning",
        "isPercent": false,
        "min": 3,
        "max": 4,
        "value": 4
       }
      ]
     },
     {
      "slotName": "Helm",
      "itemPower": 800,
      "stats": [
       {
        "name": "Maximum Life",
        "isPercent": false,
        "min": 559,
        "max": 1211,
        "value": 1211
       },
       {
        "name": "Cooldown Reduction",
        "isPercent": true,
        "min": 6.2,
        "max": 10.3,
        "value": 10.3
       },
       {
        "name": "Total Armor",
        "isPercent": true,
        "min": 3,
        "max": 7.2,
        "value": 7.2
       },
       {
        "name": "Maximum Mana",
        "isPercent": false,
        "min": 8,
        "max": 20,
        "value": 20
       }
      ]
     },
     {
      "slotName": "Focus",
      "itemPower": 800,
      "stats": [
       {
        "name": "Cooldown Reduction",
        "isPercent": true,
        "min": 10.3,
        "max": 10.3,
        "value": 10.3
       },
       {
        "name": "Cooldown Reduction",
        "isPercent": true,
        "min": 6.2,
        "max": 10.3,
        "value": 10.3
       },
       {
        "name": "Critical Strike Chance",
        "isPercent": true,
        "min": 2.7,
        "max": 7.5,
        "value": 7.5
       },
       {
        "name": "Resource Generation",
        "isPercent": true,
        "min": 7.6,
        "max": 18.5,
        "value": 18.5
       },
       {
        "name": "Damage Reduction from Enemies That Are Burning",
        "isPercent": true,
        "min": 7.4,
        "max": 17.4,
        "value": 17.4
       }
      ]
     },
     {
      "slotName": "Pants",
      "itemPower": 800,
      "stats": [
       {
        "name": "Damage Reduction from Close Enemies",
        "isPercent": true,
        "min": 10.3,
        "max": 20.2,
        "value": 20.2
       },
       {
        "name": "Maximum Life",
        "isPercent": false,
        "min": 559,
        "max": 1211,
        "value": 1211
       },
       {
        "name": "Total Armor",
        "isPercent": true,
        "min": 3,
        "max": 7.2,
        "value": 7.2
       },
       {
        "name": "Damage Reduction from Enemies That Are Burning",
        "isPercent": true,
        "min": 7.4,
        "max": 17.4,
        "value": 17.4
       }
      ]
     },
     {
      "slotName": "Ring",
      "itemPower": 800,
      "stats": [
       {
        "name": "Fire Resistance",
        "isPercent": true,
        "min": 35,
        "max": 35,
        "value": 35
       },
       {
        "name": "Cold Resistance",
        "isPercent": true,
        "min": 35,
        "max": 35,
        "value": 35
       },
       {
        "name": "Critical Strike Damage",
        "isPercent": true,
        "min": 15.8,
        "max": 26.2,
        "value": 26.2
       },
       {
        "name": "Critical Strike Chance",
        "isPercent": true,
        "min": 2.7,
        "max": 7.5,
        "value": 7.5
       },
       {
        "name": "Maximum Life",
        "isPercent": false,
        "min": 559,
        "max": 1211,
        "value": 1211
       },
       {
        "name": "Lightning Critical Strike Damage",
        "isPercent": true,
        "min": 15.8,
        "max": 26.2,
        "value": 26.2
       }
      ]
     },
     {
      "slotName": "Ring",
      "itemPower": 800,
      "stats": [
       {
        "name": "Lightning Resistance",
        "isPercent": true,
        "min": 35,
        "max": 35,
        "value": 35
       },
       {
        "name": "Poison Resistance",
        "isPercent": true,
        "min": 35,
        "max": 35,
        "value": 35
       },
       {
        "name": "Resource Generation",
        "isPercent": true,
        "min": 7.6,
        "max": 18.5,
        "value": 18.5
       },
       {
        "name": "Critical Strike Chance",
        "isPercent": true,
        "min": 2.7,
        "max": 7.5,
        "value": 7.5
       },
       {
        "name": "Critical Strike Damage",
        "isPercent": true,
        "min": 15.8,
        "max": 26.2,
        "value": 26.2
       },
       {
        "name": "Vulnerable Damage",
        "isPercent": true,
        "min": 10.5,
        "max": 21,
        "value": 21
       }
      ]
     }
    ]
   },
   {
    "name": "Fire Ball Sorcerer Endgame Guide",
    "slots": [
     {
      "slotName": "Wand",
      "itemPower": 820,
      "stats": [
       {
        "name": "Lucky Hit Chance",
        "isPercent": true,
        "min": 15,
        "max": 15,
        "value": 15
       },
       {
        "name": "Vulnerable Damage",
        "isPercent": true,
        "min": 10.5,
        "max": 21,
        "value": 21
       },
       {
        "name": "Critical Strike Damage",
        "isPercent": true,
        "min": 15.8,
        "max": 26.2,
        "value": 26.2
       },
       {
        "name": "Core Skill Damage",
        "isPercent": true,
        "min": 18.8,
        "max": 29.3,
        "value": 29.3
       },
       {
        "name": "Intelligence",
        "isPercent": false,
        "min": 57,
        "max": 78,
        "value": 78
       }
      ]
     },
     {
      "slotName": "Amulet",
      "itemPower": 820,
      "stats": [
       {
        "name": "Resistance to All Elements",
        "isPercent": true,
        "min": 26.5,
        "max": 26.5,
        "value": 26.5
       },
       {
        "name": "Mana Cost Reduction",
        "isPercent": true,
        "min": 13.9,
        "max": 23.7,
        "value": 23.7
       },
       {
        "name": "Cooldown Reduction",
        "isPercent": true,
        "min": 6.2,
        "max": 10.3,
        "value": 10.3
       },
       {
        "name": "Ranks of All Defensive Skills",
        "isPercent": false,
        "min": 1,
        "max": 3,
        "value": 3
       },
       {
        "name": "Movement Speed",
        "isPercent": true,
        "min": 15.8,
        "max": 26.2,
        "value": 26.2
       }
      ]
     },
     {
      "slotName": "Chest Armor",
      "itemPower": 820,
      "stats": [
       {
        "name": "Intelligence",
        "isPercent": false,
        "min": 42,
        "max": 63,
        "value": 63
       },
       {
        "name": "Damage to Close Enemies",
        "isPercent": true,
        "min": 24.8,
        "max": 35.3,
        "value": 35.3
       },
       {
        "name": "Damage to Stunned Enemies",
        "isPercent": true,
        "min": 24.8,
        "max": 35.3,
        "value": 35.3
       },
       {
        "name": "Rank of the Glass Cannon Passive",
        "isPercent": false,
        "min": 1,
        "max": 1,
        "value": 1
       }
      ]
     },
     {
      "slotName": "Boots",
      "itemPower": 820,
      "stats": [
       {
        "name": "Movement Speed",
        "isPercent": true,
        "min": 15.8,
        "max": 26.2,
        "value": 26.2
       },
       {
        "name": "Movement Speed for",
        "isPercent": true,
        "min": 21,
        "max": 42,
        "value": 42
       },
       {
        "name": "Shrine Buff Duration",
        "isPercent": true,
        "min": 7.5,
        "max": 18,
        "value": 18
       },
       {
        "name": "Slow Duration Reduction",
        "isPercent": true,
        "min": 18.9,
        "max": 28.4,
        "value": 28.4
       }
      ]
     },
     {
      "slotName": "Gloves",
      "itemPower": 800,
      "stats": [
       {
        "name": "Critical Strike Chance",
        "isPercent": true,
        "min": 4.5,
        "max": 12,
        "value": 12
       },
       {
        "name": "Fireball Attack Speed",
        "isPercent": true,
        "min": 6.3,
        "max": 10.5,
        "value": 10.5
       },
       {
        "name": "Ranks of Fireball",
        "isPercent": false,
        "min": 3,
        "max": 4,
        "value": 4
       }
      ]
     },
     {
      "slotName": "Helm",
      "itemPower": 820,
      "stats": [
       {
        "name": "Cooldown Reduction",
        "isPercent": true,
        "min": 6.2,
        "max": 10.3,
        "value": 10.3
       },
       {
        "name": "Maximum Mana",
        "isPercent": false,
        "min": 8,
        "max": 20,
        "value": 20
       },
       {
        "name": "Lucky Hit Chance while You Have a Barrier",
        "isPercent": true,
        "min": 6.6,
        "max": 15,
        "value": 15
       },
       {
        "name": "Total Armor",
        "isPercent": true,
        "min": 3,
        "max": 7.2,
        "value": 7.2
       }
      ]
     },
     {
      "slotName": "Focus",
      "itemPower": 820,
      "stats": [
       {
        "name": "Cooldown Reduction",
        "isPercent": true,
        "min": 10.3,
        "max": 10.3,
        "value": 10.3
       },
       {
        "name": "Cooldown Reduction",
        "isPercent": true,
        "min": 6.2,
        "max": 10.3,
        "value": 10.3
       },
       {
        "name": "Resource Generation",
        "isPercent": true,
        "min": 7.6,
        "max": 18.5,
        "value": 18.5
       },
       {
        "name": "Mana Cost Reduction",
        "isPercent": true,
        "min": 6.2,
        "max": 10.3,
        "value": 10.3
       },
       {
        "name": "Critical Strike Chance",
        "isPercent": true,
        "min": 2.7,
        "max": 7.5,
        "value": 7.5
       }
      ]
     },
     {
      "slotName": "Pants",
      "itemPower": 820,
      "stats": [
       {
        "name": "Damage Reduction from Distant Enemies",
        "isPercent": true,
        "min": 13.9,
        "max": 23.7,
        "value": 23.7
       },
       {
        "name": "Damage Reduction from Close Enemies",
        "isPercent": true,
        "min": 10.3,
        "max": 20.2,
        "value": 20.2
       },
       {
        "name": "Damage Reduction from Enemies That Are Burning",
        "isPercent": true,
        "min": 7.4,
        "max": 17.4,
        "value": 17.4
       },
       {
        "name": "Damage Reduction",
        "isPercent": true,
        "min": 4.6,
        "max": 10.7,
        "value": 10.7
       }
      ]
     },
     {
      "slotName": "Ring",
      "itemPower": 820,
      "stats": [
       {
        "name": "Fire Resistance",
        "isPercent": true,
        "min": 35,
        "max": 35,
        "value": 35
       },
       {
        "name": "Cold Resistance",
        "isPercent": true,
        "min": 35,
        "max": 35,
        "value": 35
       },
       {
        "name": "Resource Generation",
        "isPercent": true,
        "min": 7.6,
        "max": 18.5,
        "value": 18.5
       },
       {
        "name": "Critical Strike Chance",
        "isPercent": true,
        "min": 2.7,
        "max": 7.5,
        "value": 7.5
       },
       {
        "name": "Vulnerable Damage",
        "isPercent": true,
        "min": 10.5,
        "max": 21,
        "value": 21
       },
       {
        "name": "Critical Strike Damage",
        "isPercent": true,
        "min": 15.8,
        "max": 26.2,
        "value": 26.2
       }
      ]
     },
     {
      "slotName": "Ring",
      "itemPower": 820,
      "stats": [
       {
        "name": "Fire Resistance",
        "isPercent": true,
        "min": 35,
        "max": 35,
        "value": 35
       },
       {
        "name": "Cold Resistance",
        "isPercent": true,
        "min": 35,
        "max": 35,
        "value": 35
       },
       {
        "name": "Resource Generation",
        "isPercent": true,
        "min": 7.6,
        "max": 18.5,
        "value": 18.5
       },
       {
        "name": "Critical Strike Chance",
        "isPercent": true,
        "min": 2.7,
        "max": 7.5,
        "value": 7.5
       },
       {
        "name": "Critical Strike Damage",
        "isPercent": true,
        "min": 15.8,
        "max": 26.2,
        "value": 26.2
       },
       {
        "name": "Vulnerable Damage",
        "isPercent": true,
        "min": 10.5,
        "max": 21,
        "value": 21
       }
      ]
     }
    ]
   },
   {
    "name": "Hammer of the Ancients Barbarian Endgame Build Guide",
    "slots": [
     {
      "slotName": "Sword",
      "itemPower": 820,
      "stats": [
       {
        "name": "Critical Strike Damage",
        "isPercent": true,
        "min": 10.5,
        "max": 10.5,
        "value": 26.2
       },
       {
        "name": "Vulnerable Damage",
        "isPercent": true,
        "min": 10.5,
        "max": 21,
        "value": 21
       },
       {
        "name": "Critical Strike Damage",
        "isPercent": true,
        "min": 15.8,
        "max": 26.2,
        "value": 26.2
       },
       {
        "name": "All Stats",
        "isPercent": false,
        "min": 30,
        "max": 42,
        "value": 42
       },
       {
        "name": "Damage to Close Enemies",
        "isPercent": true,
        "min": 24.8,
        "max": 35.3,
        "value": 35.3
       }
      ]
     },
     {
      "slotName": "Sword",
      "itemPower": 820,
      "stats": [
       {
        "name": "Critical Strike Damage",
        "isPercent": true,
        "min": 10.5,
        "max": 10.5,
        "value": 26.2
       },
       {
        "name": "Vulnerable Damage",
        "isPercent": true,
        "min": 10.5,
        "max": 21,
        "value": 21
       },
       {
        "name": "Critical Strike Damage",
        "isPercent": true,
        "min": 15.8,
        "max": 26.2,
        "value": 26.2
       },
       {
        "name": "All Stats",
        "isPercent": false,
        "min": 30,
        "max": 42,
        "value": 42
       },
       {
        "name": "Damage to Close Enemies",
        "isPercent": true,
        "min": 24.8,
        "max": 35.3,
        "value": 35.3
       }
      ]
     },
     {
      "slotName": "Two-Handed Mace",
      "itemPower": 820,
      "stats": [
       {
        "name": "Overpower Damage",
        "isPercent": true,
        "min": 94.5,
        "max": 94.5,
        "value": 94.5
       },
       {
        "name": "Vulnerable Damage",
        "isPercent": true,
        "min": 21,
        "max": 42,
        "value": 42
       },
       {
        "name": "Critical Strike Damage",
        "isPercent": true,
        "min": 31.5,
        "max": 52.5,
        "value": 52.5
       },
       {
        "name": "Strength",
        "isPercent": false,
        "min": 114,
        "max": 156,
        "value": 156
       },
       {
        "name": "Damage to Close Enemies",
        "isPercent": true,
        "min": 49.5,
        "max": 70.5,
        "value": 70.5
       }
      ]
     },
     {
      "slotName": "Sword",
      "itemPower": 820,
      "stats": [
       {
        "name": "Critical Strike Damage",
        "isPercent": true,
        "min": 21,
        "max": 21,
        "value": 52.5
       },
       {
        "name": "Vulnerable Damage",
        "isPercent": true,
        "min": 21,
        "max": 42,
        "value": 42
       },
       {
        "name": "Critical Strike Damage",
        "isPercent": true,
        "min": 31.5,
        "max": 52.5,
        "value": 52.5
       },
       {
        "name": "Strength",
        "isPercent": false,
        "min": 114,
        "max": 156,
        "value": 156
       },
       {
        "name": "Damage to Close Enemies",
        "isPercent": true,
        "min": 49.5,
        "max": 70.5,
        "value": 70.5
       }
      ]
     },
     {
      "slotName": "Amulet",
      "itemPower": 820,
      "stats": [
       {
        "name": "Resistance to All Elements",
        "isPercent": true,
        "min": 26.5,
        "max": 26.5,
        "value": 26.5
       },
       {
        "name": "Cooldown Reduction",
        "isPercent": true,
        "min": 6.2,
        "max": 10.3,
        "value": 10.3
       },
       {
        "name": "Ranks of the Counteroffensive Passive",
        "isPercent": false,
        "min": 1,
        "max": 3,
        "value": 3
       },
       {
        "name": "Fury Cost Reduction",
        "isPercent": true,
        "min": 13.9,
        "max": 23.7,
        "value": 23.7
       },
       {
        "name": "Movement Speed",
        "isPercent": true,
        "min": 15.8,
        "max": 26.2,
        "value": 26.2
       }
      ]
     },
     {
      "slotName": "Chest Armor",
      "itemPower": 820,
      "stats": [
       {
        "name": "Total Armor",
        "isPercent": true,
        "min": 3,
        "max": 7.2,
        "value": 7.2
       },
       {
        "name": "Damage Reduction while Fortified",
        "isPercent": true,
        "min": 7.3,
        "max": 15.3,
        "value": 15.3
       },
       {
        "name": "Damage Reduction from Close Enemies",
        "isPercent": true,
        "min": 10.3,
        "max": 20.2,
        "value": 20.2
       },
       {
        "name": "Ranks of Challenging Shout",
        "isPercent": false,
        "min": 3,
        "max": 4,
        "value": 4
       }
      ]
     },
     {
      "slotName": "Boots",
      "itemPower": 820,
      "stats": [
       {
        "name": "Max Evade Charges",
        "isPercent": false,
        "min": 3,
        "max": 3,
        "value": 3
       },
       {
        "name": "Movement Speed",
        "isPercent": true,
        "min": 15.8,
        "max": 26.2,
        "value": 26.2
       },
       {
        "name": "Fury Cost Reduction",
        "isPercent": true,
        "min": 6.2,
        "max": 10.3,
        "value": 10.3
       },
       {
        "name": "Berserking Duration",
        "isPercent": true,
        "min": 21,
        "max": 31.5,
        "value": 31.5
       },
       {
        "name": "Strength",
        "isPercent": false,
        "min": 42,
        "max": 63,
        "value": 63
       }
      ]
     },
     {
      "slotName": "Gloves",
      "itemPower": 820,
      "stats": [
       {
        "name": "Ranks of Hammer of the Ancients",
        "isPercent": false,
        "min": 3,
        "max": 4,
        "value": 4
       },
       {
        "name": "Critical Strike Chance",
        "isPercent": true,
        "min": 4.5,
        "max": 12,
        "value": 12
       },
       {
        "name": "Lucky Hit Chance",
        "isPercent": true,
        "min": 8.1,
        "max": 16.5,
        "value": 16.5
       },
       {
        "name": "Attack Speed",
        "isPercent": true,
        "min": 6.6,
        "max": 15,
        "value": 15
       }
      ]
     },
     {
      "slotName": "Helm",
      "itemPower": 820,
      "stats": [
       {
        "name": "Cooldown Reduction",
        "isPercent": true,
        "min": 6.2,
        "max": 10.3,
        "value": 10.3
       },
       {
        "name": "Total Armor",
        "isPercent": true,
        "min": 3,
        "max": 7.2,
        "value": 7.2
       },
       {
        "name": "Maximum Fury",
        "isPercent": false,
        "min": 8,
        "max": 20,
        "value": 20
       },
       {
        "name": "Maximum Life",
        "isPercent": false,
        "min": 605,
        "max": 1310,
        "value": 1310
       }
      ]
     },
     {
      "slotName": "Pants",
      "itemPower": 820,
      "stats": [
       {
        "name": "All Stats",
        "isPercent": false,
        "min": 15,
        "max": 27,
        "value": 27
       },
       {
        "name": "Potion Drop Rate",
        "isPercent": true,
        "min": 18,
        "max": 39,
        "value": 39
       },
       {
        "name": "Healing Received",
        "isPercent": true,
        "min": 10.5,
        "max": 21,
        "value": 21
       }
      ]
     },
     {
      "slotName": "Ring",
      "itemPower": 820,
      "stats": [
       {
        "name": "Fire Resistance",
        "isPercent": true,
        "min": 35,
        "max": 35,
        "value": 35
       },
       {
        "name": "Cold Resistance",
        "isPercent": true,
        "min": 35,
        "max": 35,
        "value": 35
       },
       {
        "name": "Vulnerable Damage",
        "isPercent": true,
        "min": 10.5,
        "max": 21,
        "value": 21
       },
       {
        "name": "Critical Strike Chance",
        "isPercent": true,
        "min": 2.7,
        "max": 7.5,
        "value": 7.5
       },
       {
        "name": "Resource Generation",
        "isPercent": true,
        "min": 7.6,
        "max": 18.5,
        "value": 18.5
       },
       {
        "name": "Maximum Fury",
        "isPercent": false,
        "min": 5,
        "max": 14,
        "value": 14
       }
      ]
     },
     {
      "slotName": "Ring",
      "itemPower": 820,
      "stats": [
       {
        "name": "Fire Resistance",
        "isPercent": true,
        "min": 35,
        "max": 35,
        "value": 35
       },
       {
        "name": "Cold Resistance",
        "isPercent": true,
        "min": 35,
        "max": 35,
        "value": 35
       },
       {
        "name": "Vulnerable Damage",
        "isPercent": true,
        "min": 10.5,
        "max": 21,
        "value": 21
       },
       {
        "name": "Critical Strike Chance",
        "isPercent": true,
        "min": 2.7,
        "max": 7.5,
        "value": 7.5
       },
       {
        "name": "Resource Generation",
        "isPercent": true,
        "min": 7.6,
        "max": 18.5,
        "value": 18.5
       },
       {
        "name": "Maximum Fury",
        "isPercent": false,
        "min": 5,
        "max": 14,
        "value": 14
       }
      ]
     }
    ]
   },
   {
    "name": "Ice Shards Sorcerer Endgame Guide",
    "slots": [
     {
      "slotName": "Wand",
      "itemPower": 800,
      "stats": [
       {
        "name": "Lucky Hit Chance",
        "isPercent": true,
        "min": 15,
        "max": 15,
        "value": 15
       },
       {
        "name": "Core Skill Damage",
        "isPercent": true,
        "min": 18.8,
        "max": 29.3,
        "value": 29.3
       },
       {
        "name": "Critical Strike Damage",
        "isPercent": true,
        "min": 15.8,
        "max": 26.2,
        "value": 26.2
       },
       {
        "name": "Vulnerable Damage",
        "isPercent": true,
        "min": 10.5,
        "max": 21,
        "value": 21
       },
       {
        "name": "Intelligence",
        "isPercent": false,
        "min": 57,
        "max": 78,
        "value": 78
       }
      ]
     },
     {
      "slotName": "Amulet",
      "itemPower": 800,
      "stats": [
       {
        "name": "Resistance to All Elements",
        "isPercent": true,
        "min": 26.5,
        "max": 26.5,
        "value": 26.5
       },
       {
        "name": "Ranks of the Devouring Blaze Passive",
        "isPercent": false,
        "min": 1,
        "max": 3,
        "value": 3
       },
       {
        "name": "Cooldown Reduction",
        "isPercent": true,
        "min": 6.2,
        "max": 10.3,
        "value": 10.3
       },
       {
        "name": "Mana Cost Reduction",
        "isPercent": true,
        "min": 13.9,
        "max": 23.7,
        "value": 23.7
       },
       {
        "name": "Ranks of All Defensive Skills",
        "isPercent": false,
        "min": 1,
        "max": 3,
        "value": 3
       }
      ]
     },
     {
      "slotName": "Chest Armor",
      "itemPower": 800,
      "stats": [
       {
        "name": "Intelligence",
        "isPercent": false,
        "min": 42,
        "max": 63,
        "value": 63
       },
       {
        "name": "Damage to Close Enemies",
        "isPercent": true,
        "min": 24.8,
        "max": 35.3,
        "value": 35.3
       },
       {
        "name": "Damage to Stunned Enemies",
        "isPercent": true,
        "min": 24.8,
        "max": 35.3,
        "value": 35.3
       },
       {
        "name": "Rank of the Glass Cannon Passive",
        "isPercent": false,
        "min": 1,
        "max": 1,
        "value": 1
       }
      ]
     },
     {
      "slotName": "Boots",
      "itemPower": 800,
      "stats": [
       {
        "name": "Max Evade Charges",
        "isPercent": false,
        "min": 3,
        "max": 3,
        "value": 3
       },
       {
        "name": "Ranks of Frost Nova",
        "isPercent": false,
        "min": 3,
        "max": 4,
        "value": 4
       },
       {
        "name": "Mana Cost Reduction",
        "isPercent": true,
        "min": 6.2,
        "max": 10.3,
        "value": 10.3
       },
       {
        "name": "Ranks of Flame Shield",
        "isPercent": false,
        "min": 3,
        "max": 4,
        "value": 4
       },
       {
        "name": "Movement Speed",
        "isPercent": true,
        "min": 15.8,
        "max": 26.2,
        "value": 26.2
       }
      ]
     },
     {
      "slotName": "Gloves",
      "itemPower": 800,
      "stats": [
       {
        "name": "Critical Strike Chance",
        "isPercent": true,
        "min": 4.5,
        "max": 12,
        "value": 12
       },
       {
        "name": "Ranks of Ice Shards",
        "isPercent": false,
        "min": 3,
        "max": 4,
        "value": 4
       },
       {
        "name": "Attack Speed",
        "isPercent": true,
        "min": 6.6,
        "max": 15,
        "value": 15
       },
       {
        "name": "Lucky Hit Chance",
        "isPercent": true,
        "min": 8.1,
        "max": 16.5,
        "value": 16.5
       }
      ]
     },
     {
      "slotName": "Chest Armor",
      "itemPower": 800,
      "stats": [
       {
        "name": "Intelligence",
        "isPercent": false,
        "min": 42,
        "max": 63,
        "value": 63
       },
       {
        "name": "Damage to Close Enemies",
        "isPercent": true,
        "min": 24.8,
        "max": 35.3,
        "value": 35.3
       },
       {
        "name": "Damage to Stunned Enemies",
        "isPercent": true,
        "min": 24.8,
        "max": 35.3,
        "value": 35.3
       },
       {
        "name": "Rank of the Glass Cannon Passive",
        "isPercent": false,
        "min": 1,
        "max": 1,
        "value": 1
       }
      ]
     },
     {
      "slotName": "Focus",
      "itemPower": 800,
      "stats": [
       {
        "name": "Cooldown Reduction",
        "isPercent": true,
        "min": 10.3,
        "max": 10.3,
        "value": 10.3
       },
       {
        "name": "Cooldown Reduction",
        "isPercent": true,
        "min": 6.2,
        "max": 10.3,
        "value": 10.3
       },
       {
        "name": "Mana Cost Reduction",
        "isPercent": true,
        "min": 6.2,
        "max": 10.3,
        "value": 10.3
       },
       {
        "name": "Resource Generation",
        "isPercent": true,
        "min": 7.6,
        "max": 18.5,
        "value": 18.5
       }
      ]
     },
     {
      "slotName": "Pants",
      "itemPower": 800,
      "stats": [
       {
        "name": "Damage Reduction from Distant Enemies",
        "isPercent": true,
        "min": 13.9,
        "max": 23.7,
        "value": 23.7
       },
       {
        "name": "Damage Reduction from Close Enemies",
        "isPercent": true,
        "min": 10.3,
        "max": 20.2,
        "value": 20.2
       },
       {
        "name": "Damage Reduction from Enemies That Are Burning",
        "isPercent": true,
        "min": 7.4,
        "max": 17.4,
        "value": 17.4
       },
       {
        "name": "Damage Reduction",
        "isPercent": true,
        "min": 4.6,
        "max": 10.7,
        "value": 10.7
       }
      ]
     },
     {
      "slotName": "Ring",
      "itemPower": 800,
      "stats": [
       {
        "name": "Lightning Resistance",
        "isPercent": true,
        "min": 35,
        "max": 35,
        "value": 35
       },
       {
        "name": "Poison Resistance",
        "isPercent": true,
        "min": 35,
        "max": 35,
        "value": 35
       },
       {
        "name": "Critical Strike Chance",
        "isPercent": true,
        "min": 2.7,
        "max": 7.5,
        "value": 7.5
       },
       {
        "name": "Resource Generation",
        "isPercent": true,
        "min": 7.6,
        "max": 18.5,
        "value": 18.5
       },
       {
        "name": "Critical Strike Damage",
        "isPercent": true,
        "min": 15.8,
        "max": 26.2,
        "value": 26.2
       },
       {
        "name": "Vulnerable Damage",
        "isPercent": true,
        "min": 10.5,
        "max": 21,
        "value": 21
       }
      ]
     },
     {
      "slotName": "Ring",
      "itemPower": 800,
      "stats": [
       {
        "name": "Fire Resistance",
        "isPercent": true,
        "min": 35,
        "max": 35,
        "value": 35
       },
       {
        "name": "Cold Resistance",
        "isPercent": true,
        "min": 35,
        "max": 35,
        "value": 35
       },
       {
        "name": "Critical Strike Damage",
        "isPercent": true,
        "min": 15.8,
        "max": 26.2,
        "value": 26.2
       },
       {
        "name": "Critical Strike Chance",
        "isPercent": true,
        "min": 2.7,
        "max": 7.5,
        "value": 7.5
       },
       {
        "name": "Resource Generation",
        "isPercent": true,
        "min": 7.6,
        "max": 18.5,
        "value": 18.5
       },
       {
        "name": "Vulnerable Damage",
        "isPercent": true,
        "min": 10.5,
        "max": 21,
        "value": 21
       }
      ]
     }
    ]
   },
   {
    "name": "Poison Shred Druid Endgame Build",
    "slots": [
     {
      "slotName": "Axe",
      "itemPower": 820,
      "stats": [
       {
        "name": "Damage to Healthy Enemies",
        "isPercent": true,
        "min": 42,
        "max": 42,
        "value": 42
       },
       {
        "name": "Vulnerable Damage",
        "isPercent": true,
        "min": 10.5,
        "max": 21,
        "value": 21
       },
       {
        "name": "Willpower",
        "isPercent": false,
        "min": 57,
        "max": 78,
        "value": 78
       },
       {
        "name": "Critical Strike Damage",
        "isPercent": true,
        "min": 15.8,
        "max": 26.2,
        "value": 26.2
       },
       {
        "name": "Critical Strike Damage with Werewolf Skills",
        "isPercent": true,
        "min": 15.8,
        "max": 26.2,
        "value": 26.2
       }
      ]
     },
     {
      "slotName": "Amulet",
      "itemPower": 820,
      "stats": [
       {
        "name": "Resistance to All Elements",
        "isPercent": true,
        "min": 26.5,
        "max": 26.5,
        "value": 26.5
       },
       {
        "name": "Cooldown Reduction",
        "isPercent": true,
        "min": 6.2,
        "max": 10.3,
        "value": 10.3
       },
       {
        "name": "Ranks of All Companion Skills",
        "isPercent": false,
        "min": 1,
        "max": 3,
        "value": 3
       },
       {
        "name": "Ranks of the Call of the Wild Passive",
        "isPercent": false,
        "min": 1,
        "max": 3,
        "value": 3
       },
       {
        "name": "Damage Reduction from Enemies That Are Poisoned",
        "isPercent": true,
        "min": 7.4,
        "max": 17.4,
        "value": 17.4
       }
      ]
     },
     {
      "slotName": "Chest Armor",
      "itemPower": 820,
      "stats": [
       {
        "name": "Damage Reduction from Enemies That Are Poisoned",
        "isPercent": true,
        "min": 7.4,
        "max": 17.4,
        "value": 17.4
       },
       {
        "name": "Damage Reduction while Fortified",
        "isPercent": true,
        "min": 7.3,
        "max": 15.3,
        "value": 15.3
       },
       {
        "name": "Damage Reduction from Close Enemies",
        "isPercent": true,
        "min": 10.3,
        "max": 20.2,
        "value": 20.2
       },
       {
        "name": "Damage Reduction from Distant Enemies",
        "isPercent": true,
        "min": 13.9,
        "max": 23.7,
        "value": 23.7
       }
      ]
     },
     {
      "slotName": "Boots",
      "itemPower": 820,
      "stats": [
       {
        "name": "Movement Speed",
        "isPercent": true,
        "min": 15.8,
        "max": 26.2,
        "value": 26.2
       },
       {
        "name": "Willpower",
        "isPercent": false,
        "min": 42,
        "max": 63,
        "value": 63
       },
       {
        "name": "Total Armor while in Werewolf Form",
        "isPercent": true,
        "min": 7.4,
        "max": 15.8,
        "value": 15.8
       },
       {
        "name": "Dodge Chance",
        "isPercent": true,
        "min": 4.5,
        "max": 8.6,
        "value": 8.6
       }
      ]
     },
     {
      "slotName": "Gloves",
      "itemPower": 820,
      "stats": [
       {
        "name": "Critical Strike Chance",
        "isPercent": true,
        "min": 4.5,
        "max": 12,
        "value": 12
       },
       {
        "name": "Attack Speed",
        "isPercent": true,
        "min": 6.6,
        "max": 15,
        "value": 15
       },
       {
        "name": "Ranks of Shred",
        "isPercent": false,
        "min": 3,
        "max": 4,
        "value": 4
       },
       {
        "name": "Lucky Hit Chance",
        "isPercent": true,
        "min": 8.1,
        "max": 16.5,
        "value": 16.5
       }
      ]
     },
     {
      "slotName": "Helm",
      "itemPower": 820,
      "stats": [
       {
        "name": "Cooldown Reduction",
        "isPercent": true,
        "min": 6.2,
        "max": 10.3,
        "value": 10.3
       },
       {
        "name": "Ranks of Poison Creeper",
        "isPercent": false,
        "min": 3,
        "max": 4,
        "value": 4
       },
       {
        "name": "Maximum Life",
        "isPercent": false,
        "min": 605,
        "max": 1310,
        "value": 1310
       },
       {
        "name": "Barrier Generation",
        "isPercent": true,
        "min": 10.5,
        "max": 21,
        "value": 21
       }
      ]
     },
     {
      "slotName": "Totem",
      "itemPower": 820,
      "stats": [
       {
        "name": "Cooldown Reduction",
        "isPercent": true,
        "min": 10.3,
        "max": 10.3,
        "value": 10.3
       },
       {
        "name": "Cooldown Reduction",
        "isPercent": true,
        "min": 6.2,
        "max": 10.3,
        "value": 10.3
       },
       {
        "name": "Critical Strike Chance",
        "isPercent": true,
        "min": 2.7,
        "max": 7.5,
        "value": 7.5
       },
       {
        "name": "Damage Reduction from Enemies That Are Poisoned",
        "isPercent": true,
        "min": 7.4,
        "max": 17.4,
        "value": 17.4
       },
       {
        "name": "Lucky Hit Chance",
        "isPercent": true,
        "min": 4.8,
        "max": 9,
        "value": 9
       }
      ]
     },
     {
      "slotName": "Pants",
      "itemPower": 820,
      "stats": [
       {
        "name": "Damage Reduction from Enemies That Are Poisoned",
        "isPercent": true,
        "min": 7.4,
        "max": 17.4,
        "value": 17.4
       },
       {
        "name": "Damage Reduction while Fortified",
        "isPercent": true,
        "min": 7.3,
        "max": 15.3,
        "value": 15.3
       },
       {
        "name": "Damage Reduction from Close Enemies",
        "isPercent": true,
        "min": 10.3,
        "max": 20.2,
        "value": 20.2
       },
       {
        "name": "Damage Reduction from Distant Enemies",
        "isPercent": true,
        "min": 13.9,
        "max": 23.7,
        "value": 23.7
       }
      ]
     },
     {
      "slotName": "Ring",
      "itemPower": 820,
      "stats": [
       {
        "name": "Fire Resistance",
        "isPercent": true,
        "min": 35,
        "max": 35,
        "value": 35
       },
       {
        "name": "Cold Resistance",
        "isPercent": true,
        "min": 35,
        "max": 35,
        "value": 35
       },
       {
        "name": "Critical Strike Chance",
        "isPercent": true,
        "min": 2.7,
        "max": 7.5,
        "value": 7.5
       },
       {
        "name": "Vulnerable Damage",
        "isPercent": true,
        "min": 10.5,
        "max": 21,
        "value": 21
       },
       {
        "name": "Lucky Hit Chance",
        "isPercent": true,
        "min": 4.8,
        "max": 9,
        "value": 9
       },
       {
        "name": "Critical Strike Damage",
        "isPercent": true,
        "min": 15.8,
        "max": 26.2,
        "value": 26.2
       }
      ]
     },
     {
      "slotName": "Ring",
      "itemPower": 820,
      "stats": [
       {
        "name": "Lightning Resistance",
        "isPercent": true,
        "min": 35,
        "max": 35,
        "value": 35
       },
       {
        "name": "Shadow Resistance",
        "isPercent": true,
        "min": 35,
        "max": 35,
        "value": 35
       },
       {
        "name": "Vulnerable Damage",
        "isPercent": true,
        "min": 10.5,
        "max": 21,
        "value": 21
       },
       {
        "name": "Critical Strike Chance",
        "isPercent": true,
        "min": 2.7,
        "max": 7.5,
        "value": 7.5
       },
       {
        "name": "Critical Strike Damage",
        "isPercent": true,
        "min": 15.8,
        "max": 26.2,
        "value": 26.2
       },
       {
        "name": "Lucky Hit Chance",
        "isPercent": true,
        "min": 4.8,
        "max": 9,
        "value": 9
       }
      ]
     }
    ]
   },
   {
    "name": "Sever Necromancer Endgame Guide",
    "slots": [
     {
      "slotName": "Sword",
      "itemPower": 800,
      "stats": [
       {
        "name": "Critical Strike Damage",
        "isPercent": true,
        "min": 21,
        "max": 21,
        "value": 21
       },
       {
        "name": "Critical Strike Damage",
        "isPercent": true,
        "min": 31.5,
        "max": 52.5,
        "value": 52.5
       },
       {
        "name": "Vulnerable Damage",
        "isPercent": true,
        "min": 21,
        "max": 42,
        "value": 42
       },
       {
        "name": "Core Skill Damage",
        "isPercent": true,
        "min": 37.5,
        "max": 58.5,
        "value": 58.5
       },
       {
        "name": "Damage to Affected By Shadow Damage Over Time Enemies",
        "isPercent": true,
        "min": 21,
        "max": 42,
        "value": 42
       }
      ]
     },
     {
      "slotName": "Amulet",
      "itemPower": 800,
      "stats": [
       {
        "name": "Resistance to All Elements",
        "isPercent": true,
        "min": 26.5,
        "max": 26.5,
        "value": 26.5
       },
       {
        "name": "Essence Cost Reduction",
        "isPercent": true,
        "min": 13.9,
        "max": 23.7,
        "value": 23.7
       },
       {
        "name": "Ranks of the Gloom Passive",
        "isPercent": false,
        "min": 1,
        "max": 3,
        "value": 3
       },
       {
        "name": "Movement Speed",
        "isPercent": true,
        "min": 15.8,
        "max": 26.2,
        "value": 26.2
       },
       {
        "name": "Ranks of All Corpse Skills",
        "isPercent": false,
        "min": 1,
        "max": 3,
        "value": 3
       }
      ]
     },
     {
      "slotName": "Chest Armor",
      "itemPower": 800,
      "stats": [
       {
        "name": "Damage Reduction from Close Enemies",
        "isPercent": true,
        "min": 10.3,
        "max": 20.2,
        "value": 20.2
       },
       {
        "name": "Total Armor",
        "isPercent": true,
        "min": 3,
        "max": 7.2,
        "value": 7.2
       },
       {
        "name": "Maximum Life",
        "isPercent": false,
        "min": 559,
        "max": 1211,
        "value": 1211
       },
       {
        "name": "Damage Reduction from Enemies That Are Affected By Shadow Damage Over Time",
        "isPercent": true,
        "min": 7.4,
        "max": 17.4,
        "value": 17.4
       }
      ]
     },
     {
      "slotName": "Boots",
      "itemPower": 800,
      "stats": [
       {
        "name": "Max Evade Charges",
        "isPercent": false,
        "min": 3,
        "max": 3,
        "value": 3
       },
       {
        "name": "Movement Speed",
        "isPercent": true,
        "min": 15.8,
        "max": 26.2,
        "value": 26.2
       },
       {
        "name": "Essence Cost Reduction",
        "isPercent": true,
        "min": 6.2,
        "max": 10.3,
        "value": 10.3
       },
       {
        "name": "Lucky Hit Chance with Shadow Damage",
        "isPercent": true,
        "min": 6.6,
        "max": 15,
        "value": 15
       },
       {
        "name": "Damage Reduction from Enemies That Are Affected By Shadow Damage Over Time",
        "isPercent": true,
        "min": 7.4,
        "max": 17.4,
        "value": 17.4
       }
      ]
     },
     {
      "slotName": "Gloves",
      "itemPower": 800,
      "stats": [
       {
        "name": "Ranks of Sever",
        "isPercent": false,
        "min": 3,
        "max": 4,
        "value": 4
       },
       {
        "name": "Attack Speed",
        "isPercent": true,
        "min": 6.6,
        "max": 15,
        "value": 15
       },
       {
        "name": "Critical Strike Chance",
        "isPercent": true,
        "min": 4.5,
        "max": 12,
        "value": 12
       }
      ]
     },
     {
      "slotName": "Helm",
      "itemPower": 800,
      "stats": [
       {
        "name": "Maximum Life",
        "isPercent": false,
        "min": 559,
        "max": 1211,
        "value": 1211
       },
       {
        "name": "Total Armor",
        "isPercent": true,
        "min": 3,
        "max": 7.2,
        "value": 7.2
       },
       {
        "name": "Cooldown Reduction",
        "isPercent": true,
        "min": 6.2,
        "max": 10.3,
        "value": 10.3
       },
       {
        "name": "Lucky Hit Chance while You Have a Barrier",
        "isPercent": true,
        "min": 6.6,
        "max": 15,
        "value": 15
       }
      ]
     },
     {
      "slotName": "Pants",
      "itemPower": 800,
      "stats": [
       {
        "name": "Ranks of Corpse Explosion",
        "isPercent": false,
        "min": 3,
        "max": 4,
        "value": 4
       },
       {
        "name": "Total Armor",
        "isPercent": true,
        "min": 3,
        "max": 7.2,
        "value": 7.2
       },
       {
        "name": "Maximum Life",
        "isPercent": false,
        "min": 559,
        "max": 1211,
        "value": 1071
       },
       {
        "name": "Damage Reduction from Enemies That Are Affected By Shadow Damage Over Time",
        "isPercent": true,
        "min": 7.4,
        "max": 17.4,
        "value": 17.4
       }
      ]
     },
     {
      "slotName": "Ring",
      "itemPower": 800,
      "stats": [
       {
        "name": "Fire Resistance",
        "isPercent": true,
        "min": 35,
        "max": 35,
        "value": 35
       },
       {
        "name": "Cold Resistance",
        "isPercent": true,
        "min": 35,
        "max": 35,
        "value": 35
       },
       {
        "name": "Critical Strike Chance",
        "isPercent": true,
        "min": 2.7,
        "max": 7.5,
        "value": 7.5
       },
       {
        "name": "Critical Strike Damage",
        "isPercent": true,
        "min": 15.8,
        "max": 26.2,
        "value": 31.5
       },
       {
        "name": "Vulnerable Damage",
        "isPercent": true,
        "min": 10.5,
        "max": 21,
        "value": 35.3
       },
       {
        "name": "Lucky Hit Chance",
        "isPercent": true,
        "min": 4.8,
        "max": 9,
        "value": 9
       }
      ]
     },
     {
      "slotName": "Ring",
      "itemPower": 800,
      "stats": [
       {
        "name": "Lightning Resistance",
        "isPercent": true,
        "min": 35,
        "max": 35,
        "value": 35
       },
       {
        "name": "Poison Resistance",
        "isPercent": true,
        "min": 35,
        "max": 35,
        "value": 35
       },
       {
        "name": "Critical Strike Chance",
        "isPercent": true,
        "min": 2.7,
        "max": 7.5,
        "value": 7.5
       },
       {
        "name": "Critical Strike Damage",
        "isPercent": true,
        "min": 15.8,
        "max": 26.2,
        "value": 31.5
       },
       {
        "name": "Vulnerable Damage",
        "isPercent": true,
        "min": 10.5,
        "max": 21,
        "value": 35.3
       },
       {
        "name": "Lucky Hit Chance",
        "isPercent": true,
        "min": 4.8,
        "max": 9,
        "value": 9
       }
      ]
     }
    ]
   },
   {
    "name": "Thorns Barbarian Endgame Guide",
    "slots": [
     {
      "slotName": "Axe",
      "itemPower": 820,
      "stats": [
       {
        "name": "Damage to Healthy Enemies",
        "isPercent": true,
        "min": 42,
        "max": 42,
        "value": 42
       },
       {
        "name": "Vulnerable Damage",
        "isPercent": true,
        "min": 10.5,
        "max": 21,
        "value": 21
       },
       {
        "name": "Strength",
        "isPercent": false,
        "min": 57,
        "max": 78,
        "value": 78
       },
       {
        "name": "All Stats",
        "isPercent": false,
        "min": 30,
        "max": 42,
        "value": 42
       },
       {
        "name": "Damage to Close Enemies",
        "isPercent": true,
        "min": 24.8,
        "max": 35.3,
        "value": 35.3
       }
      ]
     },
     {
      "slotName": "Axe",
      "itemPower": 820,
      "stats": [
       {
        "name": "Damage to Healthy Enemies",
        "isPercent": true,
        "min": 42,
        "max": 42,
        "value": 42
       },
       {
        "name": "Vulnerable Damage",
        "isPercent": true,
        "min": 10.5,
        "max": 21,
        "value": 21
       },
       {
        "name": "Strength",
        "isPercent": false,
        "min": 57,
        "max": 78,
        "value": 78
       },
       {
        "name": "All Stats",
        "isPercent": false,
        "min": 30,
        "max": 42,
        "value": 42
       },
       {
        "name": "Damage to Close Enemies",
        "isPercent": true,
        "min": 24.8,
        "max": 35.3,
        "value": 35.3
       }
      ]
     },
     {
      "slotName": "Two-Handed Mace",
      "itemPower": 820,
      "stats": [
       {
        "name": "Overpower Damage",
        "isPercent": true,
        "min": 94.5,
        "max": 94.5,
        "value": 94.5
       },
       {
        "name": "Vulnerable Damage",
        "isPercent": true,
        "min": 21,
        "max": 42,
        "value": 42
       },
       {
        "name": "Strength",
        "isPercent": false,
        "min": 114,
        "max": 156,
        "value": 156
       },
       {
        "name": "All Stats",
        "isPercent": false,
        "min": 60,
        "max": 84,
        "value": 84
       },
       {
        "name": "Damage to Close Enemies",
        "isPercent": true,
        "min": 49.5,
        "max": 70.5,
        "value": 70.5
       }
      ]
     },
     {
      "slotName": "Axe",
      "itemPower": 820,
      "stats": [
       {
        "name": "Damage to Healthy Enemies",
        "isPercent": true,
        "min": 84,
        "max": 84,
        "value": 84
       },
       {
        "name": "Vulnerable Damage",
        "isPercent": true,
        "min": 21,
        "max": 42,
        "value": 42
       },
       {
        "name": "Strength",
        "isPercent": false,
        "min": 114,
        "max": 156,
        "value": 156
       },
       {
        "name": "All Stats",
        "isPercent": false,
        "min": 60,
        "max": 84,
        "value": 84
       },
       {
        "name": "Damage to Close Enemies",
        "isPercent": true,
        "min": 49.5,
        "max": 70.5,
        "value": 70.5
       }
      ]
     },
     {
      "slotName": "Amulet",
      "itemPower": 820,
      "stats": [
       {
        "name": "Resistance to All Elements",
        "isPercent": true,
        "min": 26.5,
        "max": 26.5,
        "value": 26.5
       },
       {
        "name": "Cooldown Reduction",
        "isPercent": true,
        "min": 6.2,
        "max": 10.3,
        "value": 10.3
       },
       {
        "name": "Damage Reduction while Fortified",
        "isPercent": true,
        "min": 7.3,
        "max": 15.3,
        "value": 15.3
       },
       {
        "name": "Damage Reduction from Close Enemies",
        "isPercent": true,
        "min": 10.3,
        "max": 20.2,
        "value": 20.2
       },
       {
        "name": "Ranks of All Defensive Skills",
        "isPercent": false,
        "min": 1,
        "max": 3,
        "value": 3
       }
      ]
     },
     {
      "slotName": "Boots",
      "itemPower": 820,
      "stats": [
       {
        "name": "Max Evade Charges",
        "isPercent": false,
        "min": 3,
        "max": 3,
        "value": 3
       },
       {
        "name": "Movement Speed",
        "isPercent": true,
        "min": 15.8,
        "max": 26.2,
        "value": 26.2
       },
       {
        "name": "Strength",
        "isPercent": false,
        "min": 42,
        "max": 63,
        "value": 63
       },
       {
        "name": "Berserking Duration",
        "isPercent": true,
        "min": 21,
        "max": 31.5,
        "value": 31.5
       },
       {
        "name": "Damage Reduction while Injured",
        "isPercent": true,
        "min": 25.1,
        "max": 43.3,
        "value": 43.3
       }
      ]
     },
     {
      "slotName": "Gloves",
      "itemPower": 820,
      "stats": [
       {
        "name": "Attack Speed",
        "isPercent": true,
        "min": 6.6,
        "max": 15,
        "value": 15
       },
       {
        "name": "Strength",
        "isPercent": false,
        "min": 42,
        "max": 63,
        "value": 63
       },
       {
        "name": "Damage to Injured Enemies",
        "isPercent": true,
        "min": 31.5,
        "max": 52.5,
        "value": 52.5
       },
       {
        "name": "All Stats",
        "isPercent": false,
        "min": 15,
        "max": 27,
        "value": 27
       }
      ]
     },
     {
      "slotName": "Helm",
      "itemPower": 820,
      "stats": [
       {
        "name": "Cooldown Reduction",
        "isPercent": true,
        "min": 6.2,
        "max": 10.3,
        "value": 10.3
       },
       {
        "name": "Total Armor",
        "isPercent": true,
        "min": 3,
        "max": 7.2,
        "value": 7.2
       },
       {
        "name": "Maximum Life",
        "isPercent": false,
        "min": 605,
        "max": 1310,
        "value": 1310
       },
       {
        "name": "Strength",
        "isPercent": false,
        "min": 42,
        "max": 63,
        "value": 63
       }
      ]
     },
     {
      "slotName": "Pants",
      "itemPower": 820,
      "stats": [
       {
        "name": "Total Armor",
        "isPercent": true,
        "min": 3,
        "max": 7.2,
        "value": 7.2
       },
       {
        "name": "Damage Reduction while Fortified",
        "isPercent": true,
        "min": 7.3,
        "max": 15.3,
        "value": 15.3
       },
       {
        "name": "Damage Reduction",
        "isPercent": true,
        "min": 4.6,
        "max": 10.7,
        "value": 10.7
       },
       {
        "name": "Berserking Duration",
        "isPercent": true,
        "min": 21,
        "max": 31.5,
        "value": 31.5
       }
      ]
     },
     {
      "slotName": "Ring",
      "itemPower": 820,
      "stats": [
       {
        "name": "Fire Resistance",
        "isPercent": true,
        "min": 35,
        "max": 35,
        "value": 35
       },
       {
        "name": "Cold Resistance",
        "isPercent": true,
        "min": 35,
        "max": 35,
        "value": 35
       },
       {
        "name": "Vulnerable Damage",
        "isPercent": true,
        "min": 10.5,
        "max": 21,
        "value": 21
       },
       {
        "name": "Maximum Life",
        "isPercent": false,
        "min": 605,
        "max": 1310,
        "value": 1310
       },
       {
        "name": "Damage to Close Enemies",
        "isPercent": true,
        "min": 24.8,
        "max": 35.3,
        "value": 35.3
       },
       {
        "name": "Damage while Berserking",
        "isPercent": true,
        "min": 10.5,
        "max": 21,
        "value": 21
       }
      ]
     },
     {
      "slotName": "Ring",
      "itemPower": 820,
      "stats": [
       {
        "name": "Fire Resistance",
        "isPercent": true,
        "min": 35,
        "max": 35,
        "value": 35
       },
       {
        "name": "Cold Resistance",
        "isPercent": true,
        "min": 35,
        "max": 35,
        "value": 35
       },
       {
        "name": "Vulnerable Damage",
        "isPercent": true,
        "min": 10.5,
        "max": 21,
        "value": 21
       },
       {
        "name": "Maximum Life",
        "isPercent": false,
        "min": 605,
        "max": 1310,
        "value": 1310
       },
       {
        "name": "Damage to Close Enemies",
        "isPercent": true,
        "min": 24.8,
        "max": 35.3,
        "value": 35.3
       },
       {
        "name": "Damage while Berserking",
        "isPercent": true,
        "min": 10.5,
        "max": 21,
        "value": 21
       }
      ]
     }
    ]
   },
   {
    "name": "Trampleslide Druid Endgame Build",
    "slots": [
     {
      "slotName": "Axe",
      "itemPower": 820,
      "stats": [
       {
        "name": "Damage to Healthy Enemies",
        "isPercent": true,
        "min": 42,
        "max": 42,
        "value": 42
       },
       {
        "name": "Vulnerable Damage",
        "isPercent": true,
        "min": 10.5,
        "max": 21,
        "value": 21
       },
       {
        "name": "Critical Strike Damage",
        "isPercent": true,
        "min": 15.8,
        "max": 26.2,
        "value": 26.2
       },
       {
        "name": "Critical Strike Damage with Earth Skills",
        "isPercent": true,
        "min": 15.8,
        "max": 26.2,
        "value": 26.2
       },
       {
        "name": "Core Skill Damage",
        "isPercent": true,
        "min": 18.8,
        "max": 29.3,
        "value": 29.3
       }
      ]
     },
     {
      "slotName": "Amulet",
      "itemPower": 820,
      "stats": [
       {
        "name": "Resistance to All Elements",
        "isPercent": true,
        "min": 26.5,
        "max": 26.5,
        "value": 26.5
       },
       {
        "name": "Ranks of the Envenom Passive",
        "isPercent": false,
        "min": 1,
        "max": 3,
        "value": 3
       },
       {
        "name": "Movement Speed",
        "isPercent": true,
        "min": 15.8,
        "max": 26.2,
        "value": 26.2
       },
       {
        "name": "Damage Reduction while Fortified",
        "isPercent": true,
        "min": 7.3,
        "max": 15.3,
        "value": 15.3
       },
       {
        "name": "Cooldown Reduction",
        "isPercent": true,
        "min": 6.2,
        "max": 10.3,
        "value": 10.3
       }
      ]
     },
     {
      "slotName": "Chest Armor",
      "itemPower": 820,
      "stats": [
       {
        "name": "Damage Reduction while Fortified",
        "isPercent": true,
        "min": 7.3,
        "max": 15.3,
        "value": 15.3
       },
       {
        "name": "Damage Reduction from Enemies That Are Poisoned",
        "isPercent": true,
        "min": 7.4,
        "max": 17.4,
        "value": 17.4
       },
       {
        "name": "Damage Reduction from Close Enemies",
        "isPercent": true,
        "min": 10.3,
        "max": 20.2,
        "value": 20.2
       },
       {
        "name": "Damage Reduction from Distant Enemies",
        "isPercent": true,
        "min": 13.9,
        "max": 23.7,
        "value": 23.7
       }
      ]
     },
     {
      "slotName": "Boots",
      "itemPower": 820,
      "stats": [
       {
        "name": "Max Evade Charges",
        "isPercent": false,
        "min": 3,
        "max": 3,
        "value": 3
       },
       {
        "name": "Movement Speed",
        "isPercent": true,
        "min": 15.8,
        "max": 26.2,
        "value": 26.2
       },
       {
        "name": "Movement Speed for",
        "isPercent": true,
        "min": 21,
        "max": 42,
        "value": 42
       },
       {
        "name": "Dodge Chance",
        "isPercent": true,
        "min": 4.5,
        "max": 8.6,
        "value": 8.6
       },
       {
        "name": "Willpower",
        "isPercent": false,
        "min": 42,
        "max": 63,
        "value": 63
       }
      ]
     },
     {
      "slotName": "Gloves",
      "itemPower": 820,
      "stats": [
       {
        "name": "Ranks of Landslide",
        "isPercent": false,
        "min": 3,
        "max": 4,
        "value": 4
       },
       {
        "name": "Critical Strike Chance",
        "isPercent": true,
        "min": 4.5,
        "max": 12,
        "value": 12
       },
       {
        "name": "Attack Speed",
        "isPercent": true,
        "min": 6.6,
        "max": 15,
        "value": 15
       },
       {
        "name": "Critical Strike Damage with Earth Skills",
        "isPercent": true,
        "min": 15.8,
        "max": 26.2,
        "value": 26.2
       }
      ]
     },
     {
      "slotName": "Helm",
      "itemPower": 820,
      "stats": [
       {
        "name": "Cooldown Reduction",
        "isPercent": true,
        "min": 6.2,
        "max": 10.3,
        "value": 10.3
       },
       {
        "name": "Basic Skill Attack Speed",
        "isPercent": true,
        "min": 6.6,
        "max": 15,
        "value": 15
       },
       {
        "name": "Total Armor",
        "isPercent": true,
        "min": 3,
        "max": 7.2,
        "value": 7.2
       },
       {
        "name": "Maximum Life",
        "isPercent": false,
        "min": 605,
        "max": 1310,
        "value": 1310
       }
      ]
     },
     {
      "slotName": "Totem",
      "itemPower": 820,
      "stats": [
       {
        "name": "Cooldown Reduction",
        "isPercent": true,
        "min": 10.3,
        "max": 10.3,
        "value": 10.3
       },
       {
        "name": "Critical Strike Chance",
        "isPercent": true,
        "min": 2.7,
        "max": 7.5,
        "value": 7.5
       },
       {
        "name": "Cooldown Reduction",
        "isPercent": true,
        "min": 6.2,
        "max": 10.3,
        "value": 10.3
       },
       {
        "name": "Damage Reduction while Fortified",
        "isPercent": true,
        "min": 7.3,
        "max": 15.3,
        "value": 15.3
       },
       {
        "name": "Damage Reduction from Enemies That Are Poisoned",
        "isPercent": true,
        "min": 7.4,
        "max": 17.4,
        "value": 17.4
       }
      ]
     },
     {
      "slotName": "Pants",
      "itemPower": 820,
      "stats": [
       {
        "name": "Damage Reduction while Fortified",
        "isPercent": true,
        "min": 7.3,
        "max": 15.3,
        "value": 15.3
       },
       {
        "name": "Damage Reduction from Enemies That Are Poisoned",
        "isPercent": true,
        "min": 7.4,
        "max": 17.4,
        "value": 17.4
       },
       {
        "name": "Damage Reduction from Close Enemies",
        "isPercent": true,
        "min": 10.3,
        "max": 20.2,
        "value": 20.2
       },
       {
        "name": "Damage Reduction from Distant Enemies",
        "isPercent": true,
        "min": 13.9,
        "max": 23.7,
        "value": 23.7
       }
      ]
     },
     {
      "slotName": "Ring",
      "itemPower": 820,
      "stats": [
       {
        "name": "Fire Resistance",
        "isPercent": true,
        "min": 35,
        "max": 35,
        "value": 35
       },
       {
        "name": "Cold Resistance",
        "isPercent": true,
        "min": 35,
        "max": 35,
        "value": 35
       },
       {
        "name": "Critical Strike Chance",
        "isPercent": true,
        "min": 2.7,
        "max": 7.5,
        "value": 7.5
       },
       {
        "name": "Vulnerable Damage",
        "isPercent": true,
        "min": 10.5,
        "max": 21,
        "value": 21
       },
       {
        "name": "Critical Strike Damage",
        "isPercent": true,
        "min": 15.8,
        "max": 26.2,
        "value": 26.2
       },
       {
        "name": "Critical Strike Damage with Earth Skills",
        "isPercent": true,
        "min": 15.8,
        "max": 26.2,
        "value": 26.2
       }
      ]
     },
     {
      "slotName": "Ring",
      "itemPower": 820,
      "stats": [
       {
        "name": "Lightning Resistance",
        "isPercent": true,
        "min": 35,
        "max": 35,
        "value": 35
       },
       {
        "name": "Poison Resistance",
        "isPercent": true,
        "min": 35,
        "max": 35,
        "value": 35
       },
       {
        "name": "Critical Strike Chance",
        "isPercent": true,
        "min": 2.7,
        "max": 7.5,
        "value": 7.5
       },
       {
        "name": "Vulnerable Damage",
        "isPercent": true,
        "min": 10.5,
        "max": 21,
        "value": 21
       },
       {
        "name": "Critical Strike Damage",
        "isPercent": true,
        "min": 15.8,
        "max": 26.2,
        "value": 26.2
       },
       {
        "name": "Critical Strike Damage with Earth Skills",
        "isPercent": true,
        "min": 15.8,
        "max": 26.2,
        "value": 26.2
       }
      ]
     }
    ]
   },
   {
    "name": "Walking Arsenal Barbarian Endgame Guide",
    "slots": [
     {
      "slotName": "Sword",
      "itemPower": 820,
      "stats": [
       {
        "name": "Critical Strike Damage",
        "isPercent": true,
        "min": 10.5,
        "max": 10.5,
        "value": 26.2
       },
       {
        "name": "Vulnerable Damage",
        "isPercent": true,
        "min": 10.5,
        "max": 21,
        "value": 21
       },
       {
        "name": "Critical Strike Damage",
        "isPercent": true,
        "min": 15.8,
        "max": 26.2,
        "value": 26.2
       },
       {
        "name": "Strength",
        "isPercent": false,
        "min": 57,
        "max": 78,
        "value": 78
       },
       {
        "name": "All Stats",
        "isPercent": false,
        "min": 30,
        "max": 42,
        "value": 42
       }
      ]
     },
     {
      "slotName": "Sword",
      "itemPower": 820,
      "stats": [
       {
        "name": "Critical Strike Damage",
        "isPercent": true,
        "min": 10.5,
        "max": 10.5,
        "value": 26.2
       },
       {
        "name": "Vulnerable Damage",
        "isPercent": true,
        "min": 10.5,
        "max": 21,
        "value": 21
       },
       {
        "name": "Critical Strike Damage",
        "isPercent": true,
        "min": 15.8,
        "max": 26.2,
        "value": 26.2
       },
       {
        "name": "Strength",
        "isPercent": false,
        "min": 57,
        "max": 78,
        "value": 78
       },
       {
        "name": "All Stats",
        "isPercent": false,
        "min": 30,
        "max": 42,
        "value": 42
       }
      ]
     },
     {
      "slotName": "Two-Handed Mace",
      "itemPower": 820,
      "stats": [
       {
        "name": "Overpower Damage",
        "isPercent": true,
        "min": 94.5,
        "max": 94.5,
        "value": 94.5
       },
       {
        "name": "Physical Damage",
        "isPercent": true,
        "min": 31.5,
        "max": 52.5,
        "value": 42
       },
       {
        "name": "Overpower Damage",
        "isPercent": true,
        "min": 63,
        "max": 126,
        "value": 126
       },
       {
        "name": "Damage to Injured Enemies",
        "isPercent": true,
        "min": 63,
        "max": 105,
        "value": 105
       },
       {
        "name": "Critical Strike Chance Against Injured Enemies",
        "isPercent": true,
        "min": 13.5,
        "max": 36,
        "value": 36
       }
      ]
     },
     {
      "slotName": "Axe",
      "itemPower": 820,
      "stats": [
       {
        "name": "Damage to Healthy Enemies",
        "isPercent": true,
        "min": 84,
        "max": 84,
        "value": 84
       },
       {
        "name": "All Stats",
        "isPercent": false,
        "min": 60,
        "max": 84,
        "value": 84
       },
       {
        "name": "Critical Strike Damage",
        "isPercent": true,
        "min": 31.5,
        "max": 52.5,
        "value": 52.5
       },
       {
        "name": "Strength",
        "isPercent": false,
        "min": 114,
        "max": 156,
        "value": 156
       },
       {
        "name": "Vulnerable Damage",
        "isPercent": true,
        "min": 21,
        "max": 42,
        "value": 42
       }
      ]
     },
     {
      "slotName": "Amulet",
      "itemPower": 820,
      "stats": [
       {
        "name": "Resistance to All Elements",
        "isPercent": true,
        "min": 26.5,
        "max": 26.5,
        "value": 26.5
       },
       {
        "name": "Ranks of the Heavy Handed Passive",
        "isPercent": false,
        "min": 1,
        "max": 3,
        "value": 3
       },
       {
        "name": "Movement Speed",
        "isPercent": true,
        "min": 15.8,
        "max": 26.2,
        "value": 26.2
       },
       {
        "name": "Cooldown Reduction",
        "isPercent": true,
        "min": 6.2,
        "max": 10.3,
        "value": 10.3
       },
       {
        "name": "Ranks of All Weapon Mastery Skills",
        "isPercent": false,
        "min": 1,
        "max": 3,
        "value": 3
       }
      ]
     },
     {
      "slotName": "Chest Armor",
      "itemPower": 820,
      "stats": [
       {
        "name": "Damage Reduction from Distant Enemies",
        "isPercent": true,
        "min": 13.9,
        "max": 23.7,
        "value": 23.7
       },
       {
        "name": "Damage Reduction from Close Enemies",
        "isPercent": true,
        "min": 10.3,
        "max": 20.2,
        "value": 20.2
       },
       {
        "name": "Damage Reduction",
        "isPercent": true,
        "min": 4.6,
        "max": 10.7,
        "value": 10.7
       },
       {
        "name": "Damage Reduction while Fortified",
        "isPercent": true,
        "min": 7.3,
        "max": 15.3,
        "value": 15.3
       }
      ]
     },
     {
      "slotName": "Boots",
      "itemPower": 820,
      "stats": [
       {
        "name": "Max Evade Charges",
        "isPercent": false,
        "min": 3,
        "max": 3,
        "value": 3
       },
       {
        "name": "Movement Speed",
        "isPercent": true,
        "min": 15.8,
        "max": 26.2,
        "value": 26.2
       },
       {
        "name": "Movement Speed for",
        "isPercent": true,
        "min": 21,
        "max": 42,
        "value": 42
       },
       {
        "name": "Berserking Duration",
        "isPercent": true,
        "min": 21,
        "max": 31.5,
        "value": 31.5
       },
       {
        "name": "Fortify Generation",
        "isPercent": true,
        "min": 22.5,
        "max": 33,
        "value": 33
       }
      ]
     },
     {
      "slotName": "Gloves",
      "itemPower": 820,
      "stats": [
       {
        "name": "Ranks of Upheaval",
        "isPercent": false,
        "min": 3,
        "max": 4,
        "value": 4
       },
       {
        "name": "Critical Strike Chance",
        "isPercent": true,
        "min": 4.5,
        "max": 12,
        "value": 12
       },
       {
        "name": "Attack Speed",
        "isPercent": true,
        "min": 6.6,
        "max": 15,
        "value": 15
       },
       {
        "name": "Lucky Hit Chance",
        "isPercent": true,
        "min": 8.1,
        "max": 16.5,
        "value": 16.5
       }
      ]
     },
     {
      "slotName": "Helm",
      "itemPower": 820,
      "stats": [
       {
        "name": "Ranks of Death Blow",
        "isPercent": false,
        "min": 3,
        "max": 4,
        "value": 4
       },
       {
        "name": "Cooldown Reduction",
        "isPercent": true,
        "min": 6.2,
        "max": 10.3,
        "value": 10.3
       },
       {
        "name": "Total Armor",
        "isPercent": true,
        "min": 3,
        "max": 7.2,
        "value": 7.2
       },
       {
        "name": "Life On Kill",
        "isPercent": false,
        "min": 101,
        "max": 242,
        "value": 242
       }
      ]
     },
     {
      "slotName": "Pants",
      "itemPower": 820,
      "stats": [
       {
        "name": "Damage Reduction from Close Enemies",
        "isPercent": true,
        "min": 10.3,
        "max": 20.2,
        "value": 20.2
       },
       {
        "name": "Damage Reduction",
        "isPercent": true,
        "min": 4.6,
        "max": 10.7,
        "value": 10.7
       },
       {
        "name": "Damage Reduction while Fortified",
        "isPercent": true,
        "min": 7.3,
        "max": 15.3,
        "value": 15.3
       },
       {
        "name": "Damage Reduction from Enemies That Are Bleeding",
        "isPercent": true,
        "min": 7.4,
        "max": 17.4,
        "value": 20.2
       }
      ]
     },
     {
      "slotName": "Ring",
      "itemPower": 820,
      "stats": [
       {
        "name": "Lightning Resistance",
        "isPercent": true,
        "min": 35,
        "max": 35,
        "value": 35
       },
       {
        "name": "Poison Resistance",
        "isPercent": true,
        "min": 35,
        "max": 35,
        "value": 35
       },
       {
        "name": "Critical Strike Damage",
        "isPercent": true,
        "min": 15.8,
        "max": 26.2,
        "value": 26.2
       },
       {
        "name": "Vulnerable Damage",
        "isPercent": true,
        "min": 10.5,
        "max": 21,
        "value": 21
       },
       {
        "name": "Critical Strike Chance",
        "isPercent": true,
        "min": 2.7,
        "max": 7.5,
        "value": 7.5
       },
       {
        "name": "Maximum Life",
        "isPercent": false,
        "min": 605,
        "max": 1310,
        "value": 1310
       }
      ]
     },
     {
      "slotName": "Ring",
      "itemPower": 820,
      "stats": [
       {
        "name": "Fire Resistance",
        "isPercent": true,
        "min": 35,
        "max": 35,
        "value": 35
       },
       {
        "name": "Cold Resistance",
        "isPercent": true,
        "min": 35,
        "max": 35,
        "value": 35
       },
       {
        "name": "Vulnerable Damage",
        "isPercent": true,
        "min": 10.5,
        "max": 21,
        "value": 21
       },
       {
        "name": "Critical Strike Damage",
        "isPercent": true,
        "min": 15.8,
        "max": 26.2,
        "value": 26.2
       },
       {
        "name": "Critical Strike Chance",
        "isPercent": true,
        "min": 2.7,
        "max": 7.5,
        "value": 7.5
       },
       {
        "name": "Fortify Generation",
        "isPercent": true,
        "min": 22.5,
        "max": 33,
        "value": 33
       }
      ]
     }
    ]
   }
  ]
 }
]